{
 "mdsDat": {
 "x": [ -0.03322109, -0.03254923, -0.2134266, -0.1262381, 0.1555833, 0.09868074, 0.1511709 ],
"y": [ 0.0993886, 0.006826246, -0.0314937, -0.05968029, 0.02097693, 0.1628942, -0.198912 ],
"topics": [ 1, 2, 3, 4, 5, 6, 7 ],
"Freq": [ 20.50255, 16.42851, 16.33822, 12.09061, 11.98728, 11.67832,  10.9745 ],
"cluster": [        1,        1,        1,        1,        1,        1,        1 ] 
},
"tinfo": {
 "Term": [ "wetland", "offset", "biodivers", "mitig", "compens", "bank", "conserv", "ecosystem", "permit", "loss", "stream", "environment", "market", "credit", "impact", "restor", "marin", "measur", "servic", "net", "econom", "habitat", "plan", "speci", "ecolog", "water", "polici", "project", "govern", "avail", "avert", "bycatch", "otherwis", "draft", "aichi", "mammal", "nnlnpi", "plantat", "extinct", "india", "migratori", "npi", "pitfal", "preexist", "stronger", "uzbekistan", "-go", "ambatovi", "confid", "hcv", "like--lik", "madagascar", "momentum", "national-level", "ocean", "pauciti", "portfolio", "queensland", "realist", "satellit", "marin", "eia", "bat", "coher", "iaia", "reef", "rout", "railway", "spain", "ant", "connot", "provinci", "workabl", "african", "member", "confirm", "cab", "colombia", "natura", "coral", "greenfield", "offshor", "reinforc", "semi-natur", "solid", "spanish", "switzerland", "wild", "absent", "berlin", "acreag", "marsh", "freshwat", "aco", "florida", "dredg", "flood", "francisco", "louisiana", "nationwid", "templat", "request", "wet", "age", "estuarin", "palustrin", "tidal", "gulf", "master", "michigan", "offic", "ohio", "season", "varianc", "alabama", "gis", "harbor", "hydrogeomorph", "indiana", "northern", "stream", "delay", "colorado", "effluent", "mangrov", "electr", "volunt", "dispar", "downstream", "facil", "landhold", "passag", "creek", "candid", "congress", "packag", "surplus", "-front", "april", "dioxid", "fine-scal", "rancher", "revenu", "statut", "overlap", "anecdot", "contributor", "disagre", "ephemer", "headwat", "mbis", "eco-compens", "contract", "licens", "safetea-lu", "alloc", "bdo", "normat", "royal", "shed", "citizen", "csr", "scholar", "transnat", "abroad", "avenu", "bbop", "democraci", "disput", "ecotour", "informa", "massiv", "mediat", "norm", "rescal", "societ", "designmethodologyapproach", "enrich", "hypothesi", "legaci", "abstract", "iucn", "capita", "agenda", "collat", "conservatori", "inequ", "least-cost", "peer-review", "socio-ecolog", "socio-polit", "academi", "hundr", "induc", "multin", "nineteenth", "none", "phrase", "suburb", "multipli", "exclus", "bad", "multi-criteria", "amen", "seem", "flora", "viabl", "sphere", "fourth", "licenc", "avail", "commod", "sold", "palm", "cap", "cap--trad", "moral", "moreov", "concentr", "skill", "antipod", "eas", "emphasis", "ever", "frontier", "sale", "spread", "prerequisit", "mobil", "activist", "automat", "bureaucrat", "cardiff", "circl", "dystopian", "gmbh", "ideal", "impetus", "launch", "legitimis", "offset", "biodivers", "target", "fisheri", "gain", "australia", "outcom", "hadd", "behaviour", "authoris", "currenc", "loss", "strict", "para", "commit", "deforest", "sea", "pervers", "compens", "measur", "zealand", "hea", "hydropow", "swedish", "dutch", "hierarchi", "duti", "great", "consent", "wetland", "permit", "corp", "armi", "section", "plant", "hydrolog", "minimum", "korea", "transport", "aquat", "-lieu", "profession", "ilf", "educ", "flow", "updat", "coal", "beij", "staff", "abl", "nepa", "actor", "china", "contest", "struggl", "well-", "content", "metaphor", "relicens", "particip", "quit", "converg", "government", "policy-mak", "ecosystem", "captur", "nnl", "reli", "cours", "compat", "inconsist", "communic", "credit", "bank", "commodif", "market", "landown", "purchas", "price", "except", "pes", "entiti", "incentiv", "entrepreneuri", "obscur", "usfw", "tradabl", "biobank", "net", "achiev", "calcul", "compani", "scheme", "conserv", "biolog", "deliv", "trajectori", "landscape-level", "legal", "environ", "principl", "avoid", "ecolog", "univers", "germani", "leakag", "direct", "wind", "success", "function", "complianc", "mitig", "site", "record", "engin", "acr", "percent", "water", "agenc", "qualiti", "advanc", "american", "fee", "mitig", "planner", "interview", "govern", "busi", "england", "right", "social", "servic", "countri", "challeng", "scientif", "equival", "tool", "broader", "link", "popular", "safeguard", "transact", "refer", "privat", "exchang", "endang", "materi", "market-bas", "time", "goal", "habitat", "clear", "explicit", "develop", "south", "global", "impact", "environment", "develop", "propos", "implement", "plan", "european", "road", "residu", "compensatori", "area", "creation", "type", "file", "act", "less", "restor", "plan", "program", "watersh", "environment", "feder", "polit", "institut", "negoti", "instrument", "account", "idea", "analysi", "public", "approach", "assess", "literatur", "consider", "object", "integr", "outlin", "human", "conserv", "speci", "land", "econom", "payment", "capit", "work", "concept", "impact", "can", "area", "speci", "benefit", "addit", "manag", "project", "damag", "mitig", "reserv", "project", "loss", "state", "requir", "result", "restor", "feder", "evalu", "impact", "regul", "project", "resourc", "state", "reduc", "provid", "polici", "biodivers", "paper", "mechan", "question", "analys", "differ", "interest", "discuss", "polici", "risk", "good", "frame", "conceptu", "habitat", "natur", "scienc", "neoliber", "demand", "polici", "use", "increas", "practic", "paper", "studi", "effect", "data", "creat", "regulatori", "act", "compensatori", "region", "clean", "popul", "fish", "respons", "practic", "implement", "econom", "data", "make", "environment", "system", "requir", "activ", "natur", "use", "current", "assess", "studi", "net", "program", "impact", "use", "includ", "benefit", "requir", "environment", "new", "econom", "offset", "case", "process", "develop", "ecolog", "provid", "ecolog", "protect", "regul", "use", "may", "valu", "restor", "site", "requir", "protect", "use", "manag", "process", "natur", "biodivers", "practic", "cost", "base", "conserv", "develop", "new", "polici", "effect", "implement", "process", "bank", "compens", "goal", "develop", "assess", "use", "develop", "evalu", "design", "regulatori", "ecosystem", "instrument", "manag", "habitat", "polici", "ecosystem", "conserv", "show", "offset", "natur", "framework", "practic", "provid", "approach", "polici", "protect", "market", "ecolog", "also", "also" ],
"logprob": [       30,       29,       28,       27,       26,       25,       24,       23,       22,       21,       20,       19,       18,       17,       16,       15,       14,       13,       12,       11,       10,        9,        8,        7,        6,        5,        4,        3,        2,        1,  -6.7719,  -6.9543,  -7.0596,  -7.3109,  -7.6474,  -7.6474,  -7.6474,  -7.6474,  -7.8706,  -7.8706,  -7.8706,  -7.8706,  -7.8706,  -7.8706,  -7.8706,  -7.8706,  -8.1582,  -8.1582,  -8.1582,  -8.1582,  -8.1582,  -8.1582,  -8.1582,  -8.1582,  -8.1582,  -8.1582,  -8.1582,  -8.1582,  -8.1582,  -8.1582,   -4.471,  -4.8765,  -6.9559,  -7.0895,  -7.0895,  -7.0895,  -7.0895,  -7.2436,  -7.2436,  -7.4259,  -7.4259,  -7.4259,  -7.4259,  -7.6491,  -7.6491,  -7.6491,  -7.6491,  -7.6491,  -7.6491,  -7.9367,  -7.9367,  -7.9367,  -7.9367,  -7.9367,  -7.9367,  -7.9367,  -7.9367,  -7.9367,  -8.3422,  -8.3422,  -6.1395,   -6.632,  -6.8326,  -6.9504,  -6.9504,   -7.084,   -7.084,   -7.084,   -7.084,   -7.084,   -7.084,  -7.2381,  -7.2381,  -7.4204,  -7.4204,  -7.4204,  -7.4204,  -7.6436,  -7.6436,  -7.6436,  -7.6436,  -7.6436,  -7.6436,  -7.6436,  -7.9313,  -7.9313,  -7.9313,  -7.9313,  -7.9313,  -7.9313,  -3.8766,  -6.2438,  -6.6492,  -6.6492,  -6.6492,  -6.7828,  -6.7828,  -6.9369,  -6.9369,  -6.9369,  -6.9369,  -6.9369,  -7.1192,  -7.3424,  -7.3424,  -7.3424,  -7.3424,  -7.6301,  -7.6301,  -7.6301,  -7.6301,  -7.6301,  -7.6301,  -7.6301,  -7.6301,  -8.0355,  -8.0355,  -8.0355,  -8.0355,  -8.0355,  -5.6757,  -5.7245,  -6.0811,  -6.1553,  -6.6408,  -6.7743,  -6.9284,  -6.9284,  -6.9284,  -6.9284,  -7.1108,  -7.1108,  -7.1108,  -7.1108,  -7.3339,  -7.3339,  -7.3339,  -7.3339,  -7.3339,  -7.3339,  -7.3339,  -7.3339,  -7.3339,  -7.3339,  -7.3339,  -7.3339,  -7.6216,  -7.6216,  -7.6216,  -7.6216,  -6.1292,  -6.7482,  -6.9024,  -7.3078,  -7.3078,  -7.3078,  -7.3078,  -7.3078,  -7.5955,  -7.5955,  -7.5955,   -8.001,   -8.001,   -8.001,   -8.001,   -8.001,   -8.001,   -8.001,   -8.001,  -5.8609,   -8.001,  -7.5955,   -8.001,   -8.001,  -6.7482,  -6.7482,  -7.0847,  -7.5956,  -7.5956,  -7.5956,  -4.6246,   -6.147,   -6.686,   -6.686,  -7.0224,  -7.0224,  -7.0224,  -7.0224,  -7.0224,  -7.2456,  -7.5333,  -7.5333,  -7.5333,  -7.5333,  -7.5333,  -7.5333,  -7.5333,  -7.5333,  -7.5333,  -7.9387,  -7.9387,  -7.9387,  -7.9387,  -7.9387,  -7.9387,  -7.9387,  -7.9387,  -7.9387,  -7.9387,  -7.9387,  -2.5438,  -2.8637,  -5.2571,  -5.6771,  -4.4853,  -5.6053,  -4.8682,  -7.1774,  -7.1774,  -7.1085,  -7.1099,  -3.7345,  -7.6474,  -7.1237,  -5.9627,  -6.1127,   -6.676,  -7.5048,  -3.1542,   -4.092,  -6.4704,  -6.5507,  -6.2388,  -6.5545,  -6.5756,  -4.9735,   -7.426,  -6.2292,  -7.6491,   -2.459,  -3.8885,  -5.6633,  -5.8518,  -5.4489,  -5.8311,  -5.9682,  -6.9664,  -7.4204,  -5.0155,  -5.5689,  -6.5314,  -6.6506,  -6.7978,  -6.9369,   -6.579,  -7.1192,  -7.1359,  -7.3424,  -7.3424,  -7.3424,  -7.3428,  -5.5013,  -5.0154,  -6.4176,  -6.4176,  -6.6408,  -6.9284,  -6.9284,  -6.9285,  -5.4277,  -7.1108,  -7.1108,  -7.1108,  -7.1108,  -3.5944,  -6.3077,  -4.6779,  -5.8801,  -7.5978,  -7.6098,  -6.4526,  -6.7501,  -3.9591,    -3.13,  -5.9238,  -3.7965,  -5.6046,   -6.234,  -5.5864,  -6.6865,  -6.0662,  -6.6992,  -6.8401,  -6.5906,  -7.0224,  -7.0224,  -6.4322,  -6.2773,  -4.3795,  -4.8431,  -5.9341,  -5.8038,   -5.345,   -3.858,  -5.8116,  -6.3229,  -7.0591,  -7.1489,  -5.0926,  -4.8865,   -4.961,  -4.8286,  -3.7707,   -6.532,  -6.5425,  -6.8409,  -5.4369,  -6.9302,  -4.7522,  -4.5899,  -5.0989,  -3.3257,  -4.5589,  -5.9879,  -5.9094,  -6.4699,  -6.2055,  -4.5741,  -4.7685,   -4.974,  -5.3356,  -6.1716,   -5.993,  -3.1625,  -6.4188,  -5.4733,  -4.2958,  -5.2692,  -5.8642,  -5.1205,  -4.8682,  -4.2321,  -4.7043,  -4.5748,  -5.2245,  -4.8681,  -4.5754,  -6.0321,  -5.7331,  -6.2924,  -6.6566,  -5.7096,  -5.5256,  -5.0048,  -5.2678,  -5.0896,  -5.8677,  -5.5219,  -5.2653,  -5.2013,  -4.4781,  -5.8354,  -6.1225,  -4.0798,  -6.2369,  -6.0038,    -3.79,  -3.8032,  -3.7527,  -5.0889,  -4.4882,  -4.6474,  -5.8537,  -6.2922,  -5.9817,  -4.7241,  -4.4531,  -5.5197,  -5.2165,  -6.3522,  -5.3898,  -6.0126,  -3.9162,   -4.327,  -4.5797,  -5.6052,  -3.7429,  -5.2266,   -5.155,  -4.9938,  -5.8187,  -5.0923,  -4.9714,  -6.2802,  -4.9622,  -5.1983,  -4.2864,  -4.2974,  -5.3695,   -5.254,   -5.196,  -5.1902,  -6.0992,  -5.6931,  -3.3864,  -4.2749,  -4.7268,  -4.3965,  -5.6924,  -5.5484,  -5.3002,  -5.1061,  -4.3715,  -4.9155,  -4.9201,  -5.0923,  -5.5589,  -5.7611,  -4.7053,  -4.4032,  -5.5377,  -4.1753,  -5.8558,  -4.3697,  -4.3717,  -4.9111,  -4.6358,  -4.8585,  -4.6098,   -5.509,  -5.0562,  -4.3047,  -4.7073,  -4.2302,  -5.0114,  -4.8341,  -5.3057,  -4.7682,  -3.8854,  -3.6375,  -4.7833,  -5.0384,  -5.6329,  -5.5518,  -4.8845,  -5.5631,  -5.1854,  -4.0918,  -5.3259,  -5.9732,  -5.9236,  -5.8761,  -4.1412,  -4.4172,  -5.4352,   -5.784,  -5.6719,   -4.543,  -4.6683,  -5.1983,  -4.9114,  -5.1115,  -5.0374,  -5.0442,  -5.1908,  -5.3551,  -5.0912,  -5.3334,  -5.0169,  -5.2712,  -5.8207,  -5.8855,  -5.7912,  -5.2794,  -4.7628,  -4.5781,  -4.8201,  -5.0383,  -5.4122,  -4.2254,  -5.0248,  -5.0571,  -5.4244,  -5.0894,  -4.8229,  -5.4379,  -5.1521,  -5.0095,  -4.9989,  -5.1815,  -4.5242,  -4.6579,  -5.1252,  -5.4221,  -4.9753,  -4.4949,  -4.9505,   -4.941,  -4.2743,  -5.1557,  -5.0158,  -4.4183,  -4.6321,  -4.9593,  -4.4218,  -4.8129,  -4.9699,  -4.5734,  -5.0819,  -5.1188,  -5.1182,  -5.4378,  -5.1017,  -5.2201,  -4.7788,  -5.1184,  -5.2228,  -5.0258,  -4.5035,   -5.006,  -5.3147,   -5.233,  -4.7992,  -4.5208,  -5.0223,  -4.7474,  -5.4099,  -5.4058,  -5.3414,  -5.1125,  -5.0637,   -5.359,  -4.8766,  -5.1732,  -4.9757,   -4.928,  -5.1917,  -5.2502,   -5.194,  -5.0918,  -5.3359,  -5.4314,  -5.1513,   -5.112,  -5.2274,   -5.099,  -5.3316,  -4.9912,  -5.2137,  -5.2655,  -5.2193,  -5.4845,  -5.5525,   -5.265,  -5.2547,  -5.3197,  -5.2586,  -5.3037,  -5.2953 ],
"loglift": [       30,       29,       28,       27,       26,       25,       24,       23,       22,       21,       20,       19,       18,       17,       16,       15,       14,       13,       12,       11,       10,        9,        8,        7,        6,        5,        4,        3,        2,        1,   1.5846,   1.5846,   1.5846,   1.5846,   1.5846,   1.5846,   1.5846,   1.5846,   1.5846,   1.5846,   1.5846,   1.5846,   1.5846,   1.5846,   1.5846,   1.5846,   1.5846,   1.5846,   1.5846,   1.5846,   1.5846,   1.5846,   1.5846,   1.5846,   1.5846,   1.5846,   1.5846,   1.5846,   1.5846,   1.5846,   1.8062,   1.8062,   1.8062,   1.8062,   1.8062,   1.8062,   1.8062,   1.8062,   1.8062,   1.8062,   1.8062,   1.8062,   1.8062,   1.8062,   1.8062,   1.8062,   1.8062,   1.8062,   1.8062,   1.8062,   1.8062,   1.8062,   1.8062,   1.8062,   1.8062,   1.8062,   1.8062,   1.8062,   1.8062,   1.8062,   1.8117,   1.8117,   1.8117,   1.8117,   1.8117,   1.8117,   1.8117,   1.8117,   1.8117,   1.8117,   1.8117,   1.8117,   1.8117,   1.8117,   1.8117,   1.8117,   1.8117,   1.8117,   1.8117,   1.8117,   1.8117,   1.8117,   1.8117,   1.8117,   1.8117,   1.8117,   1.8117,   1.8117,   1.8117,   1.8117,   2.1127,   2.1127,   2.1127,   2.1127,   2.1127,   2.1127,   2.1127,   2.1127,   2.1127,   2.1127,   2.1127,   2.1127,   2.1127,   2.1127,   2.1127,   2.1127,   2.1127,   2.1127,   2.1127,   2.1127,   2.1127,   2.1127,   2.1127,   2.1127,   2.1127,   2.1127,   2.1127,   2.1127,   2.1127,   2.1127,   2.1213,   2.1213,   2.1213,   2.1213,   2.1213,   2.1213,   2.1213,   2.1213,   2.1213,   2.1213,   2.1213,   2.1213,   2.1213,   2.1213,   2.1213,   2.1213,   2.1213,   2.1213,   2.1213,   2.1213,   2.1213,   2.1213,   2.1213,   2.1213,   2.1213,   2.1213,   2.1213,   2.1213,   2.1213,   2.1213,   2.1474,   2.1474,   2.1474,   2.1474,   2.1474,   2.1474,   2.1474,   2.1474,   2.1474,   2.1474,   2.1474,   2.1474,   2.1474,   2.1474,   2.1474,   2.1474,   2.1474,   2.1474,   2.1474,   2.1474,   2.1474,   2.1474,   2.1474,   2.1474,   2.1474,   2.1474,   2.1474,   2.1474,   2.1474,   2.1473,   2.2096,   2.2096,   2.2096,   2.2096,   2.2096,   2.2096,   2.2096,   2.2096,   2.2096,   2.2096,   2.2096,   2.2096,   2.2096,   2.2096,   2.2096,   2.2096,   2.2096,   2.2096,   2.2096,   2.2096,   2.2096,   2.2096,   2.2096,   2.2096,   2.2096,   2.2096,   2.2096,   2.2096,   2.2096,   2.2096,   1.4412,   1.2624,   1.5068,   1.5267,   1.3657,    1.475,   1.3681,   1.5846,   1.5846,   1.5358,   1.5343,   1.1511,   1.5846,   1.5206,   1.3823,   1.3966,   1.4575,   1.5449,   1.5781,    1.551,   1.8061,   1.8059,   1.7695,   1.8021,    1.781,   1.5914,   1.8061,   1.6679,   1.8062,   1.8117,   1.7326,    1.811,   1.8117,    1.729,   1.7146,   1.6952,   1.7956,   1.8117,   2.0882,   2.0944,   2.1127,   2.1114,   2.0977,   2.1127,   2.0652,   2.1127,    2.096,   2.1127,   2.1127,   2.1127,   2.1124,   2.1213,    1.976,   2.1213,   2.1213,   2.1213,   2.1213,   2.1213,   2.1213,   1.9481,   2.1213,   2.1213,   2.1213,   2.1213,   1.7875,    2.049,   1.8596,   1.9657,   2.1451,   2.1331,   1.9911,    2.012,   2.2095,   1.9977,   2.2096,   1.9574,   2.1458,   2.2096,   2.1196,   2.2091,   2.1362,   2.1964,   2.2096,   2.1714,   2.2096,   2.2096,   2.1067,   2.0792,   1.1737,   1.1006,   1.3521,      1.3,    1.179,   0.7432,   1.1797,   1.2997,   1.4798,   1.4953,   1.4862,   1.3701,   1.3807,   1.2944,   1.0211,   1.6705,     1.66,    1.698,   1.3442,   1.7141,   1.4072,    1.339,   1.4385,   0.9619,   1.2587,   1.5955,   1.5309,   1.6636,   1.5915,   1.7134,   1.6663,   1.6778,   1.7681,   1.9617,   1.9039,   1.1251,   1.9377,   1.8717,   1.5759,   1.7881,   1.9328,    1.678,   1.5789,    1.719,   1.7553,   1.7024,   1.8104,   1.6694,   1.5476,   1.8651,   1.7762,   1.9101,   1.9878,   1.7308,   1.6784,   1.8854,   1.9361,   1.8807,   1.9292,   1.8231,   1.0118,   0.9307,   0.6077,   1.1349,   1.2225,   0.3176,   1.2373,   1.1241,    0.829,   0.7902,   0.6447,   1.1474,   0.8439,   0.8958,   1.4043,   1.5047,   1.3633,   1.0675,    0.879,   1.2788,   1.1364,   1.5449,   1.1078,   1.3632,   1.2315,   1.2161,   1.2989,   1.6528,   0.8505,   1.4102,    1.626,   1.4288,   1.7647,   1.4451,   1.2954,   1.8532,   1.2842,   1.3806,   1.2668,   1.1642,   1.5803,   1.5271,   1.4712,   1.4318,   1.7979,    1.622,   1.2148,   1.3249,   1.4142,   1.2632,   1.8168,   1.7378,   1.6293,   1.5457,   0.2474,   0.5647,    0.412,   0.5074,   0.8166,   0.9372,   0.7201,    0.514,   1.1294,   0.1123,   1.2245,   0.5475,    0.514,   0.8184,   0.6147,   0.7519,   0.5379,   1.1278,   0.8225,   0.3142,   1.1103,    0.687,    1.026,   0.8954,    1.192,   0.8002,   0.7678,   0.4886,   1.0277,   1.1118,   1.4951,   1.4396,   0.9803,   1.4283,   1.3934,   0.5615,   1.3259,   1.7328,   1.6991,   1.6333,   0.9445,   1.0772,   1.6221,   1.7617,   1.6432,   0.1103,   0.1329,   0.4957,   0.5274,   0.6996,   0.5947,    0.494,   0.8885,   1.0091,   0.9966,   1.1643,   0.7747,   0.9259,   1.4372,   1.4902,   1.3867,   1.2183,   0.6761,    0.754,   0.8396,   1.0411,   1.2862,    0.368,   1.0545,   0.1934,   0.6379,    0.405,  -0.0217,   0.7592,   0.3095,   0.6226,   0.5543,   0.6971,   0.0948,   0.1434,   0.6925,   0.9535,   0.2752,   0.0986,    0.767,   0.7188,  -0.2893,   0.9497,   0.7137,   -0.021,   0.1597,   0.6092,     0.37,   0.7659,   0.8477,   0.2279,   0.9474,   0.8865,   0.0295,   0.3799,   0.1488,   0.3587,   0.0225,    0.307,   0.5067,   0.4686,  -0.3774,   0.4329,   1.0381,   0.8211,   -0.198,  -0.1234,   0.6952,  -0.0941,   0.1283,  -0.0737,   0.3881,   0.0152,  -0.3315,    0.773,  -0.4793,   0.2884,  -0.1745,  -0.5306,    0.687,    0.771,   0.8938,   0.2902,   1.2015,   -0.006,  -0.0655,  -0.4587,   0.1545,  -0.4978,   1.0792,  -1.0062,   0.2807,   0.8311,   0.2195,   0.0839,   0.0008,  -0.6118,   0.3241,   0.4342,  -0.4668,   0.6474,   0.6558 ],
"Freq": [      713,      950,      825,      702,      449,      303,      513,      234,      184,      386,      128,      517,      162,      107,      504,      297,       95,      180,      132,      198,      177,      316,      200,      189,      423,       95,      486,      374,      143,       55, 12.00037, 10.00031, 9.000281, 7.000218, 5.000156, 5.000156, 5.000156, 5.000156, 4.000125, 4.000125, 4.000125, 4.000125, 4.000125, 4.000125, 4.000125, 4.000125, 3.000094, 3.000094, 3.000094, 3.000094, 3.000094, 3.000094, 3.000094, 3.000094, 3.000094, 3.000094, 3.000094, 3.000094, 3.000094, 3.000094, 95.99878, 63.99919, 7.999899, 6.999911, 6.999911, 6.999911, 6.999911, 5.999924, 5.999924, 4.999937, 4.999937, 4.999937, 4.999937, 3.999949, 3.999949, 3.999949, 3.999949, 3.999949, 3.999949, 2.999962, 2.999962, 2.999962, 2.999962, 2.999962, 2.999962, 2.999962, 2.999962, 2.999962, 1.999975, 1.999975, 17.99943, 10.99965, 8.999716, 7.999747, 7.999747, 6.999779, 6.999779, 6.999779, 6.999779, 6.999779, 6.999779, 5.999811, 5.999811, 4.999842, 4.999842, 4.999842, 4.999842, 3.999874, 3.999874, 3.999874, 3.999874, 3.999874, 3.999874, 3.999874, 2.999905, 2.999905, 2.999905, 2.999905, 2.999905, 2.999905, 128.0116, 12.00109, 8.000726, 8.000726, 8.000726, 7.000635, 7.000635, 6.000545, 6.000545, 6.000545, 6.000545, 6.000545, 5.000454, 4.000363, 4.000363, 4.000363, 4.000363, 3.000272, 3.000272, 3.000272, 3.000272, 3.000272, 3.000272, 3.000272, 3.000272, 2.000182, 2.000182, 2.000182, 2.000182, 2.000182, 20.99939, 19.99942,  13.9996, 12.99962, 7.999769, 6.999798, 5.999827, 5.999827, 5.999827, 5.999827, 4.999855, 4.999855, 4.999855, 4.999855, 3.999884, 3.999884, 3.999884, 3.999884, 3.999884, 3.999884, 3.999884, 3.999884, 3.999884, 3.999884, 3.999884, 3.999884, 2.999913, 2.999913, 2.999913, 2.999913, 12.99899, 6.999458, 5.999535,  3.99969,  3.99969,  3.99969,  3.99969,  3.99969, 2.999768, 2.999768, 2.999768, 1.999845, 1.999845, 1.999845, 1.999845, 1.999845, 1.999845, 1.999845, 1.999845, 16.99868, 1.999845, 2.999768, 1.999845, 1.999845, 6.999458, 6.999458, 4.999613, 2.999704, 2.999576, 2.999482, 55.00119, 12.00026, 7.000152, 7.000152, 5.000109, 5.000109, 5.000109, 5.000109, 5.000109, 4.000087, 3.000065, 3.000065, 3.000065, 3.000065, 3.000065, 3.000065, 3.000065, 3.000065, 3.000065, 2.000043, 2.000043, 2.000043, 2.000043, 2.000043, 2.000043, 2.000043, 2.000043, 2.000043, 2.000043, 2.000043, 823.1005, 597.7372,  54.5837, 35.86425, 118.1042, 38.53641, 80.53203,  8.00025, 8.000246, 8.571022, 8.558928, 250.2286, 5.000147, 8.441796,  26.9558, 23.20112, 13.20921, 5.766779,  358.222,  140.241,  12.9994, 11.99719, 16.38874, 11.95172,  11.7015, 58.08304, 4.999799, 16.54588, 3.999949, 713.9775, 170.9363, 28.97942, 23.99924, 35.90552, 24.50217,   21.362, 7.872641, 4.999842, 40.98696, 23.56709, 9.000817, 7.990142, 6.895931, 6.000544,  8.58269,  5.00045, 4.917662, 4.000363, 4.000363, 4.000314,   3.9988, 24.99928, 40.64145, 9.999711, 9.999711, 7.999759, 5.999827, 5.999827, 5.999681,    26.91, 4.999855, 4.999853, 4.999844, 4.999529, 163.9608, 10.87382, 55.48867, 16.67536, 2.992884, 2.957167, 9.407323, 6.986555, 106.9949, 245.1529, 15.00028, 125.8916, 20.64165, 11.00024, 21.02167, 6.996752, 13.00976, 6.908423,  6.00013, 7.700357, 5.000109, 5.000109, 9.022586, 10.53351, 131.2855, 82.58479, 27.73855, 31.59751, 49.99402, 221.1486, 31.35141, 18.80274, 9.004676, 8.231444, 51.55769, 63.36413, 58.81034, 67.13629,  193.382, 12.22345, 12.09627,  8.97522, 36.54317, 8.208465, 72.07101, 84.77171, 50.95445, 300.1173, 87.43557, 20.94552, 22.65667, 12.93551, 16.84982, 63.72847, 52.47248, 42.72341, 29.75883, 12.89874, 15.42077,  261.458, 10.07362, 25.70869, 83.46429, 31.53152, 17.39206, 36.58746, 47.08838, 86.65384, 54.04437, 61.51563, 32.12271, 45.87855, 61.47661, 14.32509, 19.31641, 11.04144, 7.671483, 19.77648, 23.77068, 37.60363, 28.90876, 34.54598, 15.86579, 22.42127, 54.13781, 57.71765, 118.9604, 30.61618, 22.97494, 177.1728, 20.49037, 25.86955, 189.6914, 187.1878, 196.8957, 51.75105, 94.36401, 80.47906, 24.08588, 15.53506,  21.1925, 74.12031, 97.19359, 33.45325, 45.30301, 14.55083, 38.09218, 20.43513,  123.041, 81.59054,  63.3735, 22.72807, 146.3277, 33.18818, 35.34502, 41.52696, 18.20024, 37.63213, 42.46921, 11.47231, 42.86136, 33.84863,  82.0765, 81.18002,  27.7881, 31.18926, 33.05212, 33.24259, 13.39461, 20.10435, 189.7098, 78.02619, 49.65703, 69.08814, 18.90562, 21.83579, 27.98691,  33.9808, 132.3352, 76.81469, 76.46124, 64.36394, 40.36434, 32.97532, 75.94535, 102.7301, 33.03659, 129.0339, 24.03575, 105.6497, 105.4442, 61.48438, 80.96844, 64.80138,  83.0999, 33.81377, 53.17718, 112.7423, 55.78257, 89.88753, 41.15433, 49.14116, 30.66438, 52.48432, 125.8053, 161.2101, 51.25613, 39.71745, 21.91826, 23.76933, 46.32633, 23.50296, 33.40275, 99.71251, 29.02391, 15.19285, 15.96636, 16.74356, 89.18107, 67.67401, 24.45211, 17.25203, 19.29841,  111.488, 98.35327, 57.89228,  61.8002, 50.59487, 54.48795, 54.11936, 46.47889, 39.43764, 37.99726, 29.82636, 40.92964, 31.73831, 18.32078, 17.17097,  18.8701, 31.21244, 52.32214, 61.31219, 48.13297, 38.69696, 26.62576, 81.98304, 36.85879, 66.66904, 46.17541, 51.72523, 67.52137, 36.50626, 48.58205, 55.72231,  56.3123, 46.91279, 66.99353, 58.60878, 36.73056, 27.29491, 42.66961, 68.39633, 43.36613, 43.78064, 85.27526, 35.32203, 40.62462, 71.93339, 58.08754, 41.87777,  67.3629, 45.55755,  38.9396, 57.89054, 34.81276, 33.55374,   62.721, 45.56362, 51.09343, 45.38773, 70.17942, 49.96933, 33.31253, 40.21964, 66.06165, 39.96825, 29.35178, 31.85155, 49.15093,  61.0147, 36.95168, 48.64341,  46.8514, 47.04232, 40.20362, 50.26572, 52.77862, 39.28661, 47.09336, 35.00795, 42.28724,  44.3549, 33.19331, 31.30661, 31.12028, 34.47126, 27.00396, 45.85496, 48.35531, 50.29365,  33.1602, 37.38115, 29.62524, 40.56439, 32.47246, 28.97506, 30.34368, 43.48137, 40.62509, 43.39378, 32.26681, 30.23806, 31.86657, 30.46082,  29.9264 ],
"Total": [      713,      950,      825,      702,      449,      303,      513,      234,      184,      386,      128,      517,      162,      107,      504,      297,       95,      180,      132,      198,      177,      316,      200,      189,      423,       95,      486,      374,      143,       55, 12.00037, 10.00031, 9.000281, 7.000218, 5.000156, 5.000156, 5.000156, 5.000156, 4.000125, 4.000125, 4.000125, 4.000125, 4.000125, 4.000125, 4.000125, 4.000125, 3.000094, 3.000094, 3.000094, 3.000094, 3.000094, 3.000094, 3.000094, 3.000094, 3.000094, 3.000094, 3.000094, 3.000094, 3.000094, 3.000094, 95.99878, 63.99919, 7.999899, 6.999911, 6.999911, 6.999911, 6.999911, 5.999924, 5.999924, 4.999937, 4.999937, 4.999937, 4.999937, 3.999949, 3.999949, 3.999949, 3.999949, 3.999949, 3.999949, 2.999962, 2.999962, 2.999962, 2.999962, 2.999962, 2.999962, 2.999962, 2.999962, 2.999962, 1.999975, 1.999975, 17.99943, 10.99965, 8.999716, 7.999747, 7.999747, 6.999779, 6.999779, 6.999779, 6.999779, 6.999779, 6.999779, 5.999811, 5.999811, 4.999842, 4.999842, 4.999842, 4.999842, 3.999874, 3.999874, 3.999874, 3.999874, 3.999874, 3.999874, 3.999874, 2.999905, 2.999905, 2.999905, 2.999905, 2.999905, 2.999905, 128.0116, 12.00109, 8.000726, 8.000726, 8.000726, 7.000635, 7.000635, 6.000545, 6.000545, 6.000545, 6.000545, 6.000545, 5.000454, 4.000363, 4.000363, 4.000363, 4.000363, 3.000272, 3.000272, 3.000272, 3.000272, 3.000272, 3.000272, 3.000272, 3.000272, 2.000182, 2.000182, 2.000182, 2.000182, 2.000182, 20.99939, 19.99942,  13.9996, 12.99962, 7.999769, 6.999798, 5.999827, 5.999827, 5.999827, 5.999827, 4.999855, 4.999855, 4.999855, 4.999855, 3.999884, 3.999884, 3.999884, 3.999884, 3.999884, 3.999884, 3.999884, 3.999884, 3.999884, 3.999884, 3.999884, 3.999884, 2.999913, 2.999913, 2.999913, 2.999913, 12.99899, 6.999458, 5.999535,  3.99969,  3.99969,  3.99969,  3.99969,  3.99969, 2.999768, 2.999768, 2.999768, 1.999845, 1.999845, 1.999845, 1.999845, 1.999845, 1.999845, 1.999845, 1.999845, 16.99868, 1.999845, 2.999768, 1.999845, 1.999845, 6.999458, 6.999458, 4.999613, 2.999768, 2.999768, 2.999768, 55.00119, 12.00026, 7.000152, 7.000152, 5.000109, 5.000109, 5.000109, 5.000109, 5.000109, 4.000087, 3.000065, 3.000065, 3.000065, 3.000065, 3.000065, 3.000065, 3.000065, 3.000065, 3.000065, 2.000043, 2.000043, 2.000043, 2.000043, 2.000043, 2.000043, 2.000043, 2.000043, 2.000043, 2.000043, 2.000043, 950.0202, 825.0089, 59.00165, 38.00105, 147.0037, 43.00095, 100.0026,  8.00025,  8.00025, 9.000262, 9.000307, 386.0046, 5.000156, 9.000314, 33.00096, 28.00096, 15.00039, 6.000177, 449.9948, 180.9979, 12.99984, 11.99985, 16.99977, 11.99984, 11.99986, 71.99819, 4.999937, 18.99986, 3.999949, 713.9775, 184.9957, 28.99909, 23.99924, 38.99886, 26.99919, 23.99956, 7.999742, 4.999842, 42.00371, 24.00213, 9.000817, 8.000725, 7.000623, 6.000545, 9.000747, 5.000454, 5.000444, 4.000363, 4.000363, 4.000363, 4.000363, 24.99928, 46.99874, 9.999711, 9.999711, 7.999769, 5.999827, 5.999827, 5.999827, 31.99937, 4.999855, 4.999855, 4.999855, 4.999855, 234.9911, 11.99919, 73.99628, 19.99864, 2.999768,  2.99977,  10.9993, 7.999551, 107.0023, 303.0044, 15.00033, 162.0053, 22.00049, 11.00024, 23.00043, 7.000152, 14.00027, 7.000158,  6.00013, 8.000192, 5.000109, 5.000109, 10.00028, 12.00027, 198.0017, 134.0002, 35.00065, 42.00083, 75.00065, 513.0059, 47.00075, 25.00052, 10.00025, 9.000323, 70.99956, 97.99959, 89.99756, 112.0001, 423.9967, 14.00001,  13.9997, 9.999979,  58.0002, 8.999921, 107.9985, 135.9973, 73.99932, 702.0126, 151.9994, 25.99929, 29.99968, 14.99964, 20.99955,  95.0048, 82.00427, 66.00368, 42.00259, 15.00122, 19.00143, 702.0126, 12.00095, 32.99949, 143.9976, 43.99948, 20.99938, 56.99958, 80.99739, 132.9954, 79.99551, 95.99615, 44.99735, 73.99735, 111.9979, 18.99911, 27.99843, 13.99907, 8.999447, 29.99868, 37.99779, 52.00092, 38.00065, 48.00096, 21.00013,  33.0004, 96.00285, 111.0003,  316.006, 48.00049, 33.00062, 629.0008, 29.00041, 40.99996, 504.0042, 517.0112, 629.0008, 99.99958, 246.9969, 200.0062, 35.99931, 20.99981,  33.0001, 156.0008, 247.0009, 56.99885, 89.00019, 18.99962, 77.00171, 31.99929, 297.0106, 200.0062, 143.0049, 36.00164, 517.0112, 67.00194, 57.99947, 82.99926, 25.99949, 73.99946, 96.99961, 14.99974, 98.99957, 70.99893, 197.9962, 216.9962, 48.99767, 57.99777, 64.99687, 67.99814, 18.99901, 33.99881, 513.0059, 189.0041, 110.0025, 177.9967, 28.00019, 35.00009,  50.0017, 65.99921, 504.0042, 213.0016, 247.0009, 189.0041, 87.00305, 63.00065, 225.0001, 374.0031,  65.0018, 702.0126,  43.0005, 374.0031, 386.0046, 166.0029, 268.0008, 186.9998, 297.0106, 67.00194, 142.9962, 504.0042, 152.0046, 374.0031, 122.0026, 166.0029, 77.00198, 195.0023, 486.9917, 825.0089,  152.999, 108.9994, 40.99945, 46.99922, 145.0001, 46.99994, 70.99831, 486.9917, 65.99902, 22.99922,  24.9985, 27.99871,  316.006,  209.997, 43.99968, 27.00009, 34.00149, 486.9917, 420.0034, 172.0005,  221.997,  152.999, 182.9966,  201.001, 116.9962, 87.99937, 116.0024, 77.00171, 156.0008, 104.0017, 36.00112, 32.00125, 39.00205, 76.99998,  221.997, 246.9969, 177.9967, 116.9962, 62.99892, 517.0112, 116.9996, 268.0008,  119.002,  209.997, 420.0034, 103.9997, 216.9962, 182.9966, 198.0017, 143.0049, 504.0042, 420.0034, 152.0011, 87.00305, 268.0008, 517.0112, 168.0005, 177.9967, 950.0202,  113.997, 166.0007, 629.0008, 423.9967, 195.0023, 423.9967, 193.0029, 152.0046, 420.0034, 123.0029, 125.9993, 297.0106, 151.9994, 268.0008, 193.0029, 420.0034, 225.0001, 166.0007,  209.997, 825.0089,  221.997, 89.00042, 119.9974, 513.0059, 629.0008, 168.0005, 486.9917,  201.001, 246.9969, 166.0007, 303.0044, 449.9948, 111.0003, 629.0008, 216.9962, 420.0034, 629.0008, 142.9962, 123.9976, 116.0024, 234.9911, 73.99946, 225.0001,  316.006, 486.9917, 234.9911, 513.0059, 83.99705, 950.0202,  209.997, 115.0002,  221.997, 195.0023, 197.9962, 486.9917, 193.0029, 162.0053, 423.9967, 132.9991, 132.9991 ],
"Category": [ "Default", "Default", "Default", "Default", "Default", "Default", "Default", "Default", "Default", "Default", "Default", "Default", "Default", "Default", "Default", "Default", "Default", "Default", "Default", "Default", "Default", "Default", "Default", "Default", "Default", "Default", "Default", "Default", "Default", "Default", "Topic1", "Topic1", "Topic1", "Topic1", "Topic1", "Topic1", "Topic1", "Topic1", "Topic1", "Topic1", "Topic1", "Topic1", "Topic1", "Topic1", "Topic1", "Topic1", "Topic1", "Topic1", "Topic1", "Topic1", "Topic1", "Topic1", "Topic1", "Topic1", "Topic1", "Topic1", "Topic1", "Topic1", "Topic1", "Topic1", "Topic2", "Topic2", "Topic2", "Topic2", "Topic2", "Topic2", "Topic2", "Topic2", "Topic2", "Topic2", "Topic2", "Topic2", "Topic2", "Topic2", "Topic2", "Topic2", "Topic2", "Topic2", "Topic2", "Topic2", "Topic2", "Topic2", "Topic2", "Topic2", "Topic2", "Topic2", "Topic2", "Topic2", "Topic2", "Topic2", "Topic3", "Topic3", "Topic3", "Topic3", "Topic3", "Topic3", "Topic3", "Topic3", "Topic3", "Topic3", "Topic3", "Topic3", "Topic3", "Topic3", "Topic3", "Topic3", "Topic3", "Topic3", "Topic3", "Topic3", "Topic3", "Topic3", "Topic3", "Topic3", "Topic3", "Topic3", "Topic3", "Topic3", "Topic3", "Topic3", "Topic4", "Topic4", "Topic4", "Topic4", "Topic4", "Topic4", "Topic4", "Topic4", "Topic4", "Topic4", "Topic4", "Topic4", "Topic4", "Topic4", "Topic4", "Topic4", "Topic4", "Topic4", "Topic4", "Topic4", "Topic4", "Topic4", "Topic4", "Topic4", "Topic4", "Topic4", "Topic4", "Topic4", "Topic4", "Topic4", "Topic5", "Topic5", "Topic5", "Topic5", "Topic5", "Topic5", "Topic5", "Topic5", "Topic5", "Topic5", "Topic5", "Topic5", "Topic5", "Topic5", "Topic5", "Topic5", "Topic5", "Topic5", "Topic5", "Topic5", "Topic5", "Topic5", "Topic5", "Topic5", "Topic5", "Topic5", "Topic5", "Topic5", "Topic5", "Topic5", "Topic6", "Topic6", "Topic6", "Topic6", "Topic6", "Topic6", "Topic6", "Topic6", "Topic6", "Topic6", "Topic6", "Topic6", "Topic6", "Topic6", "Topic6", "Topic6", "Topic6", "Topic6", "Topic6", "Topic6", "Topic6", "Topic6", "Topic6", "Topic6", "Topic6", "Topic6", "Topic6", "Topic6", "Topic6", "Topic6", "Topic7", "Topic7", "Topic7", "Topic7", "Topic7", "Topic7", "Topic7", "Topic7", "Topic7", "Topic7", "Topic7", "Topic7", "Topic7", "Topic7", "Topic7", "Topic7", "Topic7", "Topic7", "Topic7", "Topic7", "Topic7", "Topic7", "Topic7", "Topic7", "Topic7", "Topic7", "Topic7", "Topic7", "Topic7", "Topic7", "Topic1", "Topic1", "Topic1", "Topic1", "Topic1", "Topic1", "Topic1", "Topic1", "Topic1", "Topic1", "Topic1", "Topic1", "Topic1", "Topic1", "Topic1", "Topic1", "Topic1", "Topic1", "Topic2", "Topic2", "Topic2", "Topic2", "Topic2", "Topic2", "Topic2", "Topic2", "Topic2", "Topic2", "Topic2", "Topic3", "Topic3", "Topic3", "Topic3", "Topic3", "Topic3", "Topic3", "Topic3", "Topic3", "Topic4", "Topic4", "Topic4", "Topic4", "Topic4", "Topic4", "Topic4", "Topic4", "Topic4", "Topic4", "Topic4", "Topic4", "Topic4", "Topic5", "Topic5", "Topic5", "Topic5", "Topic5", "Topic5", "Topic5", "Topic5", "Topic5", "Topic5", "Topic5", "Topic5", "Topic5", "Topic6", "Topic6", "Topic6", "Topic6", "Topic6", "Topic6", "Topic6", "Topic6", "Topic7", "Topic7", "Topic7", "Topic7", "Topic7", "Topic7", "Topic7", "Topic7", "Topic7", "Topic7", "Topic7", "Topic7", "Topic7", "Topic7", "Topic7", "Topic7", "Topic1", "Topic1", "Topic1", "Topic1", "Topic1", "Topic1", "Topic1", "Topic1", "Topic1", "Topic1", "Topic2", "Topic2", "Topic2", "Topic2", "Topic2", "Topic2", "Topic2", "Topic2", "Topic2", "Topic2", "Topic3", "Topic3", "Topic3", "Topic3", "Topic3", "Topic3", "Topic3", "Topic3", "Topic3", "Topic4", "Topic4", "Topic4", "Topic4", "Topic4", "Topic4", "Topic4", "Topic4", "Topic5", "Topic5", "Topic5", "Topic5", "Topic5", "Topic5", "Topic6", "Topic6", "Topic6", "Topic6", "Topic6", "Topic6", "Topic6", "Topic6", "Topic6", "Topic6", "Topic6", "Topic6", "Topic7", "Topic7", "Topic7", "Topic7", "Topic7", "Topic1", "Topic1", "Topic1", "Topic1", "Topic1", "Topic1", "Topic1", "Topic1", "Topic2", "Topic2", "Topic2", "Topic2", "Topic2", "Topic2", "Topic2", "Topic2", "Topic2", "Topic3", "Topic3", "Topic3", "Topic3", "Topic3", "Topic3", "Topic3", "Topic4", "Topic4", "Topic4", "Topic4", "Topic4", "Topic4", "Topic5", "Topic5", "Topic5", "Topic5", "Topic5", "Topic5", "Topic5", "Topic5", "Topic6", "Topic6", "Topic6", "Topic6", "Topic6", "Topic6", "Topic6", "Topic6", "Topic7", "Topic7", "Topic7", "Topic7", "Topic7", "Topic7", "Topic7", "Topic7", "Topic1", "Topic1", "Topic1", "Topic1", "Topic1", "Topic1", "Topic2", "Topic2", "Topic2", "Topic2", "Topic2", "Topic3", "Topic3", "Topic3", "Topic3", "Topic3", "Topic3", "Topic3", "Topic3", "Topic3", "Topic4", "Topic4", "Topic4", "Topic4", "Topic4", "Topic4", "Topic5", "Topic5", "Topic5", "Topic5", "Topic5", "Topic5", "Topic5", "Topic5", "Topic6", "Topic6", "Topic6", "Topic6", "Topic6", "Topic6", "Topic7", "Topic7", "Topic7", "Topic7", "Topic7", "Topic1", "Topic1", "Topic1", "Topic2", "Topic2", "Topic2", "Topic2", "Topic3", "Topic3", "Topic4", "Topic4", "Topic4", "Topic4", "Topic4", "Topic4", "Topic4", "Topic5", "Topic5", "Topic6", "Topic6", "Topic6", "Topic6", "Topic7", "Topic7", "Topic1", "Topic1", "Topic2", "Topic2", "Topic2", "Topic2", "Topic3", "Topic3", "Topic3", "Topic4", "Topic4", "Topic4", "Topic4", "Topic4", "Topic5", "Topic5", "Topic5", "Topic5", "Topic5", "Topic5", "Topic6", "Topic6", "Topic6", "Topic7", "Topic7", "Topic7", "Topic7", "Topic7", "Topic7", "Topic1", "Topic1", "Topic2", "Topic2", "Topic3", "Topic3", "Topic4", "Topic5", "Topic6", "Topic6", "Topic6", "Topic6", "Topic6", "Topic7", "Topic7", "Topic7", "Topic1", "Topic1", "Topic2", "Topic3", "Topic3", "Topic3", "Topic4", "Topic4", "Topic5", "Topic5", "Topic6", "Topic6", "Topic7", "Topic7", "Topic7", "Topic1", "Topic3", "Topic3", "Topic4", "Topic5", "Topic5", "Topic6", "Topic6", "Topic7", "Topic7", "Topic1", "Topic1", "Topic2", "Topic4", "Topic4", "Topic5", "Topic5", "Topic6" ] 
},
"token.table": {
 "Term": [ "-front", "-go", "-lieu", "abl", "abroad", "absent", "abstract", "academi", "account", "account", "account", "account", "account", "account", "achiev", "achiev", "achiev", "achiev", "achiev", "achiev", "aco", "acr", "acr", "acreag", "act", "act", "act", "act", "activ", "activ", "activ", "activ", "activ", "activ", "activist", "actor", "addit", "addit", "addit", "addit", "addit", "advanc", "advanc", "advanc", "advanc", "african", "age", "agenc", "agenc", "agenc", "agenda", "aichi", "alabama", "alloc", "also", "also", "also", "also", "also", "also", "also", "ambatovi", "amen", "american", "american", "analys", "analys", "analys", "analys", "analys", "analys", "analysi", "analysi", "analysi", "analysi", "analysi", "anecdot", "ant", "antipod", "approach", "approach", "approach", "approach", "approach", "approach", "approach", "april", "aquat", "area", "area", "area", "area", "area", "area", "armi", "assess", "assess", "assess", "assess", "assess", "assess", "australia", "australia", "australia", "authoris", "automat", "avail", "avenu", "avert", "avoid", "avoid", "avoid", "avoid", "bad", "bank", "bank", "bank", "base", "base", "base", "base", "base", "base", "base", "bat", "bbop", "bdo", "behaviour", "beij", "benefit", "benefit", "benefit", "benefit", "benefit", "berlin", "biobank", "biobank", "biodivers", "biodivers", "biodivers", "biolog", "biolog", "biolog", "biolog", "broader", "broader", "broader", "broader", "bureaucrat", "busi", "busi", "bycatch", "cab", "calcul", "calcul", "calcul", "can", "can", "can", "can", "can", "can", "can", "candid", "cap", "cap--trad", "capit", "capit", "capita", "captur", "captur", "cardiff", "case", "case", "case", "case", "case", "case", "case", "challeng", "challeng", "challeng", "challeng", "challeng", "china", "china", "circl", "citizen", "clean", "clean", "clean", "clear", "clear", "clear", "clear", "clear", "coal", "coher", "collat", "colombia", "colorado", "commit", "commit", "commit", "commit", "commit", "commod", "commodif", "communic", "communic", "compani", "compani", "compani", "compat", "compens", "compens", "compens", "compens", "compensatori", "compensatori", "compensatori", "compensatori", "compensatori", "complianc", "complianc", "complianc", "concentr", "concept", "concept", "concept", "concept", "conceptu", "conceptu", "conceptu", "conceptu", "confid", "confirm", "congress", "connot", "consent", "conserv", "conserv", "conserv", "conserv", "conserv", "conservatori", "consider", "consider", "consider", "consider", "consider", "content", "contest", "contract", "contributor", "converg", "coral", "corp", "cost", "cost", "cost", "cost", "cost", "cost", "countri", "countri", "countri", "countri", "cours", "creat", "creat", "creat", "creat", "creat", "creation", "creation", "creation", "creation", "credit", "creek", "csr", "currenc", "current", "current", "current", "current", "current", "current", "damag", "damag", "damag", "damag", "damag", "data", "data", "data", "data", "data", "data", "deforest", "deforest", "deforest", "delay", "deliv", "deliv", "deliv", "deliv", "deliv", "demand", "demand", "demand", "democraci", "design", "design", "design", "design", "design", "design", "designmethodologyapproach", "develop", "develop", "develop", "develop", "develop", "develop", "develop", "differ", "differ", "differ", "differ", "differ", "differ", "differ", "dioxid", "direct", "direct", "direct", "direct", "direct", "disagre", "discuss", "discuss", "discuss", "discuss", "discuss", "discuss", "dispar", "disput", "downstream", "draft", "dredg", "dutch", "duti", "dystopian", "eas", "eco-compens", "ecolog", "ecolog", "ecolog", "ecolog", "ecolog", "ecolog", "ecolog", "econom", "econom", "econom", "econom", "econom", "ecosystem", "ecosystem", "ecosystem", "ecosystem", "ecosystem", "ecotour", "educ", "effect", "effect", "effect", "effect", "effect", "effect", "effect", "effluent", "eia", "electr", "emphasis", "endang", "endang", "endang", "endang", "endang", "engin", "engin", "engin", "england", "england", "enrich", "entiti", "entrepreneuri", "environ", "environ", "environ", "environ", "environ", "environ", "environment", "environment", "environment", "environment", "environment", "environment", "environment", "ephemer", "equival", "equival", "equival", "equival", "estuarin", "european", "european", "european", "european", "european", "evalu", "evalu", "evalu", "evalu", "evalu", "ever", "except", "exchang", "exchang", "exchang", "exchang", "exclus", "explicit", "explicit", "explicit", "explicit", "extinct", "facil", "feder", "feder", "fee", "fee", "fee", "file", "file", "file", "fine-scal", "fish", "fish", "fish", "fisheri", "fisheri", "fisheri", "flood", "flora", "florida", "flow", "fourth", "frame", "frame", "framework", "framework", "framework", "framework", "framework", "francisco", "freshwat", "frontier", "function", "function", "function", "function", "function", "gain", "gain", "gain", "gain", "gain", "gain", "germani", "germani", "gis", "global", "global", "global", "global", "global", "gmbh", "goal", "goal", "goal", "goal", "goal", "good", "good", "good", "govern", "govern", "govern", "govern", "govern", "govern", "government", "great", "great", "great", "greenfield", "gulf", "habitat", "habitat", "habitat", "habitat", "habitat", "hadd", "harbor", "hcv", "hea", "headwat", "hierarchi", "hierarchi", "human", "human", "human", "human", "human", "human", "hundr", "hydrogeomorph", "hydrolog", "hydrolog", "hydropow", "hydropow", "hypothesi", "iaia", "idea", "idea", "ideal", "ilf", "impact", "impact", "impact", "impact", "impact", "impact", "impetus", "implement", "implement", "implement", "implement", "implement", "implement", "incentiv", "includ", "includ", "includ", "includ", "includ", "includ", "includ", "inconsist", "inconsist", "increas", "increas", "increas", "increas", "increas", "increas", "increas", "india", "indiana", "induc", "inequ", "informa", "institut", "institut", "institut", "institut", "institut", "instrument", "instrument", "instrument", "instrument", "integr", "integr", "integr", "integr", "interest", "interest", "interest", "interest", "interest", "interview", "interview", "interview", "iucn", "korea", "land", "land", "land", "land", "land", "landhold", "landown", "landown", "landscape-level", "landscape-level", "launch", "leakag", "leakag", "least-cost", "legaci", "legal", "legal", "legal", "legitimis", "less", "less", "less", "less", "licenc", "licens", "like--lik", "link", "link", "link", "literatur", "literatur", "literatur", "literatur", "loss", "loss", "loss", "loss", "louisiana", "madagascar", "make", "make", "make", "make", "make", "mammal", "manag", "manag", "manag", "manag", "manag", "manag", "mangrov", "marin", "market", "market", "market", "market-bas", "market-bas", "market-bas", "marsh", "massiv", "master", "materi", "materi", "materi", "materi", "may", "may", "may", "may", "may", "may", "mbis", "measur", "measur", "measur", "measur", "measur", "measur", "mechan", "mechan", "mechan", "mechan", "mechan", "mediat", "member", "metaphor", "michigan", "migratori", "minimum", "mitig", "mitig", "mitig", "mitig", "mitig", "mitig", "mobil", "momentum", "moral", "moreov", "multi-criteria", "multin", "multipli", "national-level", "nationwid", "natur", "natur", "natur", "natur", "natur", "natur", "natura", "negoti", "negoti", "negoti", "negoti", "neoliber", "neoliber", "nepa", "net", "net", "net", "net", "new", "new", "new", "new", "new", "new", "nineteenth", "nnl", "nnl", "nnlnpi", "none", "norm", "normat", "northern", "npi", "object", "object", "object", "object", "object", "obscur", "ocean", "offic", "offset", "offset", "offset", "offset", "offshor", "ohio", "otherwis", "outcom", "outcom", "outcom", "outcom", "outcom", "outlin", "outlin", "outlin", "overlap", "packag", "palm", "palustrin", "paper", "paper", "paper", "paper", "paper", "para", "para", "particip", "particip", "passag", "pauciti", "payment", "payment", "payment", "peer-review", "percent", "percent", "percent", "permit", "permit", "permit", "pervers", "pes", "pes", "phrase", "pitfal", "plan", "plan", "plan", "plan", "plan", "plan", "planner", "planner", "plant", "plant", "plantat", "polici", "polici", "polici", "polici", "polici", "polici", "polici", "policy-mak", "polit", "polit", "popul", "popul", "popul", "popul", "popul", "popul", "popular", "popular", "portfolio", "practic", "practic", "practic", "practic", "practic", "practic", "practic", "preexist", "prerequisit", "price", "price", "principl", "principl", "principl", "principl", "privat", "privat", "privat", "process", "process", "process", "process", "process", "process", "process", "profession", "program", "program", "program", "program", "program", "project", "project", "project", "project", "project", "project", "propos", "propos", "propos", "propos", "propos", "protect", "protect", "protect", "protect", "protect", "protect", "provid", "provid", "provid", "provid", "provid", "provid", "provid", "provinci", "public", "public", "public", "public", "public", "public", "purchas", "qualiti", "qualiti", "qualiti", "queensland", "question", "question", "question", "question", "question", "question", "quit", "railway", "rancher", "realist", "record", "record", "record", "record", "reduc", "reduc", "reduc", "reduc", "reduc", "reduc", "reef", "refer", "refer", "refer", "refer", "region", "region", "region", "region", "region", "region", "region", "regul", "regul", "regul", "regul", "regulatori", "regulatori", "regulatori", "regulatori", "regulatori", "reinforc", "reli", "reli", "reli", "relicens", "request", "requir", "requir", "requir", "requir", "requir", "requir", "rescal", "reserv", "reserv", "reserv", "reserv", "residu", "residu", "resourc", "resourc", "resourc", "resourc", "resourc", "resourc", "respons", "respons", "respons", "respons", "respons", "respons", "restor", "restor", "restor", "restor", "restor", "restor", "result", "result", "result", "result", "result", "result", "result", "revenu", "right", "right", "right", "risk", "risk", "risk", "risk", "risk", "risk", "road", "road", "road", "rout", "royal", "safeguard", "safeguard", "safetea-lu", "sale", "satellit", "scheme", "scheme", "scheme", "scheme", "scheme", "scheme", "scholar", "scienc", "scienc", "scienc", "scienc", "scientif", "scientif", "sea", "sea", "season", "section", "section", "section", "seem", "semi-natur", "servic", "servic", "servic", "servic", "shed", "show", "show", "show", "show", "show", "site", "site", "site", "site", "skill", "social", "social", "social", "social", "social", "societ", "socio-ecolog", "socio-polit", "sold", "solid", "south", "south", "south", "south", "spain", "spanish", "speci", "speci", "speci", "speci", "speci", "sphere", "spread", "staff", "state", "state", "state", "state", "state", "state", "statut", "stream", "strict", "stronger", "struggl", "studi", "studi", "studi", "studi", "studi", "studi", "suburb", "success", "success", "success", "success", "success", "surplus", "swedish", "switzerland", "system", "system", "system", "system", "system", "system", "target", "target", "target", "templat", "tidal", "time", "time", "time", "time", "time", "time", "tool", "tool", "tool", "tool", "tool", "tradabl", "tradabl", "trajectori", "trajectori", "transact", "transact", "transact", "transact", "transnat", "transport", "transport", "type", "type", "type", "type", "type", "univers", "univers", "updat", "use", "use", "use", "use", "use", "use", "use", "usfw", "uzbekistan", "valu", "valu", "valu", "valu", "valu", "valu", "varianc", "viabl", "volunt", "water", "water", "watersh", "watersh", "well-", "wet", "wetland", "wild", "wind", "wind", "work", "work", "work", "work", "work", "workabl", "zealand" ],
"Topic": [ 4, 1, 4, 4, 5, 2, 6, 6, 1, 2, 3, 4, 5, 6, 1, 2, 3, 4, 6, 7, 3, 3, 7, 3, 1, 3, 4, 7, 1, 2, 3, 4, 5, 7, 7, 5, 1, 2, 3, 4, 5, 1, 2, 4, 6, 2, 3, 3, 4, 7, 6, 1, 3, 5, 1, 2, 3, 4, 5, 6, 7, 1, 6, 4, 7, 1, 3, 4, 5, 6, 7, 2, 3, 4, 5, 7, 4, 2, 7, 1, 2, 3, 4, 5, 6, 7, 4, 4, 1, 2, 3, 4, 5, 6, 3, 1, 2, 3, 4, 5, 6, 1, 5, 6, 1, 7, 7, 5, 1, 1, 2, 3, 4, 6, 3, 4, 7, 1, 2, 3, 4, 5, 6, 7, 2, 5, 5, 1, 4, 1, 2, 4, 5, 6, 2, 1, 7, 1, 5, 6, 1, 3, 4, 6, 1, 2, 4, 6, 7, 1, 5, 1, 2, 1, 3, 5, 1, 2, 3, 4, 5, 6, 7, 4, 7, 7, 5, 7, 6, 1, 6, 7, 1, 2, 3, 4, 5, 6, 7, 1, 4, 5, 6, 7, 2, 5, 7, 5, 2, 3, 4, 1, 2, 3, 6, 7, 4, 2, 6, 2, 4, 1, 4, 5, 6, 7, 7, 7, 4, 6, 1, 4, 5, 6, 1, 2, 3, 5, 1, 2, 3, 4, 5, 1, 3, 4, 7, 2, 5, 6, 7, 1, 2, 5, 6, 1, 2, 4, 2, 2, 1, 2, 5, 6, 7, 6, 1, 2, 3, 6, 7, 5, 5, 5, 4, 5, 2, 3, 1, 2, 4, 5, 6, 7, 1, 2, 5, 6, 6, 2, 3, 4, 5, 7, 2, 3, 5, 7, 7, 4, 5, 1, 1, 2, 3, 4, 6, 7, 1, 2, 3, 4, 7, 2, 3, 4, 5, 6, 7, 1, 4, 5, 4, 1, 2, 3, 4, 5, 2, 4, 7, 5, 1, 2, 3, 4, 5, 6, 5, 1, 2, 3, 4, 5, 6, 7, 1, 2, 3, 4, 5, 6, 7, 4, 1, 2, 3, 4, 7, 4, 1, 2, 4, 5, 6, 7, 4, 5, 4, 1, 3, 2, 2, 7, 7, 5, 1, 2, 3, 4, 5, 6, 7, 1, 2, 5, 6, 7, 1, 2, 4, 6, 7, 5, 4, 1, 2, 3, 4, 5, 6, 7, 4, 2, 4, 7, 1, 3, 4, 6, 7, 2, 3, 4, 3, 5, 5, 7, 7, 1, 2, 4, 5, 6, 7, 1, 2, 3, 4, 5, 6, 7, 4, 1, 3, 4, 6, 3, 2, 3, 5, 6, 7, 1, 2, 3, 4, 6, 7, 7, 1, 2, 3, 7, 6, 1, 2, 3, 7, 1, 4, 3, 4, 2, 4, 7, 1, 3, 5, 4, 1, 3, 4, 1, 3, 5, 3, 6, 3, 4, 6, 5, 6, 1, 2, 3, 6, 7, 3, 3, 7, 3, 4, 5, 6, 7, 1, 2, 3, 4, 5, 7, 2, 6, 3, 1, 4, 5, 6, 7, 7, 1, 3, 4, 5, 6, 4, 6, 7, 1, 2, 4, 5, 6, 7, 5, 2, 3, 4, 2, 3, 1, 2, 3, 4, 7, 1, 3, 1, 2, 4, 2, 6, 1, 2, 3, 4, 5, 6, 6, 3, 3, 4, 2, 5, 5, 2, 5, 7, 7, 4, 1, 2, 3, 4, 5, 6, 7, 1, 2, 4, 5, 6, 7, 7, 1, 2, 3, 4, 5, 6, 7, 1, 6, 1, 2, 3, 4, 5, 6, 7, 1, 3, 6, 6, 5, 1, 4, 5, 6, 7, 1, 2, 5, 7, 2, 4, 5, 6, 1, 2, 4, 5, 7, 2, 4, 5, 6, 3, 1, 2, 3, 4, 7, 4, 1, 7, 1, 4, 7, 2, 4, 6, 5, 2, 4, 5, 7, 3, 4, 5, 6, 6, 5, 1, 5, 6, 7, 1, 4, 5, 6, 1, 2, 3, 7, 3, 1, 1, 4, 5, 6, 7, 1, 1, 2, 3, 4, 5, 7, 4, 2, 4, 5, 7, 4, 5, 7, 3, 5, 3, 3, 5, 6, 7, 1, 2, 3, 4, 5, 7, 5, 1, 2, 3, 4, 6, 7, 1, 2, 4, 5, 7, 5, 2, 5, 3, 1, 3, 1, 2, 3, 4, 6, 7, 7, 1, 7, 7, 6, 6, 6, 1, 3, 1, 2, 3, 5, 6, 7, 2, 2, 5, 6, 7, 5, 7, 4, 1, 2, 3, 6, 1, 2, 3, 4, 5, 7, 6, 1, 6, 1, 6, 5, 5, 3, 1, 2, 3, 5, 6, 7, 7, 1, 3, 1, 4, 5, 6, 2, 3, 1, 1, 3, 4, 5, 6, 1, 3, 6, 4, 4, 7, 3, 2, 4, 5, 6, 7, 1, 4, 5, 7, 4, 1, 2, 5, 7, 6, 1, 2, 3, 1, 3, 4, 1, 2, 7, 6, 1, 1, 2, 3, 4, 5, 6, 4, 7, 2, 3, 1, 1, 2, 3, 4, 5, 6, 7, 5, 5, 7, 1, 2, 3, 4, 5, 6, 5, 6, 1, 1, 2, 3, 4, 5, 6, 7, 1, 7, 2, 7, 1, 2, 5, 6, 4, 5, 7, 1, 2, 3, 4, 5, 6, 7, 4, 1, 2, 3, 4, 5, 1, 2, 3, 4, 5, 6, 1, 2, 3, 4, 6, 1, 2, 3, 4, 5, 7, 1, 2, 3, 4, 5, 6, 7, 2, 1, 2, 4, 5, 6, 7, 7, 1, 3, 4, 1, 1, 2, 3, 4, 5, 6, 5, 2, 4, 1, 1, 2, 3, 5, 1, 2, 3, 4, 5, 6, 2, 3, 5, 6, 7, 1, 2, 3, 4, 5, 6, 7, 2, 3, 4, 7, 3, 4, 5, 6, 7, 2, 3, 6, 7, 5, 3, 1, 2, 3, 4, 5, 6, 5, 2, 4, 5, 7, 1, 2, 1, 2, 3, 4, 5, 7, 1, 2, 3, 4, 5, 6, 1, 2, 3, 4, 6, 7, 1, 2, 3, 4, 5, 6, 7, 4, 2, 4, 5, 1, 2, 3, 4, 6, 7, 2, 3, 4, 2, 5, 1, 6, 5, 7, 1, 1, 2, 4, 5, 6, 7, 5, 4, 5, 6, 7, 2, 6, 1, 2, 3, 2, 3, 7, 6, 2, 3, 4, 6, 7, 5, 1, 2, 3, 5, 6, 1, 2, 3, 4, 7, 2, 4, 5, 6, 7, 5, 6, 6, 7, 2, 1, 4, 5, 6, 2, 2, 1, 3, 4, 6, 7, 6, 7, 4, 1, 2, 3, 4, 5, 7, 4, 4, 1, 1, 5, 1, 2, 3, 4, 5, 6, 6, 1, 2, 3, 4, 6, 4, 2, 2, 2, 3, 4, 5, 6, 7, 1, 4, 6, 3, 3, 1, 2, 3, 4, 5, 7, 1, 2, 4, 5, 6, 4, 7, 1, 3, 3, 4, 5, 6, 5, 2, 4, 1, 3, 4, 5, 7, 2, 4, 4, 1, 2, 3, 4, 5, 6, 7, 7, 1, 1, 2, 3, 5, 6, 7, 3, 6, 4, 3, 4, 3, 4, 5, 3, 3, 2, 1, 2, 1, 2, 3, 4, 7, 2, 2 ],
"Freq": [ 0.9999092, 0.9999688, 0.9999092, 0.9999092, 1.000029, 1.000013, 1.000077, 1.000077, 0.3402075, 0.1030932, 0.04123728, 0.04123728, 0.4329914, 0.04123728, 0.6194021, 0.03731338, 0.1194028, 0.007462676, 0.1865669, 0.0298507, 1.000032, 0.8666877, 0.1333366, 1.000032, 0.01298672, 0.4934955, 0.3896017, 0.1038938, 0.3865482, 0.04201611, 0.2520967, 0.1428548, 0.08403222, 0.1008387, 0.9999783, 1.000029, 0.5238041, 0.2063471, 0.2063471, 0.04761856, 0.01587285, 0.09523222, 0.1666564, 0.7142416, 0.04761611, 1.000013, 1.000032, 0.2560842, 0.6341133, 0.0975559, 1.000077, 0.9999688, 1.000032, 1.000029, 0.03759425, 0.150377, 0.0902262, 0.2105278, 0.2255655, 0.2255655, 0.05263195, 0.9999688, 1.000077, 0.8665964, 0.1333225, 0.1276617, 0.0851078, 0.06383085, 0.5106468, 0.1489387, 0.0851078, 0.2424253, 0.1111116, 0.1515158, 0.4343453, 0.06060632, 0.9999092, 1.000013, 0.9999783, 0.2070747, 0.1818217, 0.02020241, 0.1060627, 0.03535422, 0.4141495, 0.03535422, 0.9999092, 0.9999115, 0.3076912, 0.1174085, 0.3927112, 0.1133599, 0.04858282, 0.01619427, 1.000032, 0.110601, 0.2258104, 0.1198178, 0.1612932, 0.009216753, 0.3732785, 0.9069567, 0.0465106, 0.0697659, 0.9999709, 0.9999783, 0.9999783, 1.000029, 0.9999688, 0.3214283, 0.5982138, 0.07142851, 0.008928564, 1.000077, 0.1650141, 0.02640225, 0.808569, 0.1000022, 0.1750038, 0.2166714, 0.03333405, 0.0583346, 0.2666724, 0.1583368, 1.000013, 1.000029, 1.000029, 0.9999688, 0.9999092, 0.459754, 0.1149385, 0.3103339, 0.0459754, 0.0689631, 1.000013, 0.08333143, 0.9166457, 0.7248407, 0.1951494, 0.07999914, 0.6595639, 0.06382877, 0.1063813,  0.17021, 0.1052681, 0.05263404, 0.1052681, 0.7368766, 0.9999783, 0.2727305, 0.7272814, 0.9999688, 1.000013, 0.7999851, 0.0285709, 0.1714254, 0.3614997, 0.08920122, 0.07981162, 0.1267596, 0.1126752, 0.1361492, 0.09859083, 0.9999092, 0.9999783, 0.9999783, 0.3714276, 0.6285697, 1.000077, 0.08333894, 0.9167283, 0.9999783, 0.0438608, 0.2105318, 0.1052659, 0.03508864, 0.3070256, 0.219304, 0.07894944, 0.2187588, 0.01041708, 0.02083417, 0.6458592, 0.1041708, 0.127663, 0.8723637, 0.9999783, 1.000029, 0.02777691, 0.4722075, 0.4999844, 0.6458267, 0.06249936, 0.08333248, 0.1041656, 0.1041656, 0.9999112, 1.000013, 1.000077, 1.000013, 0.9999092, 0.8181579, 0.06060429, 0.06060429, 0.03030215, 0.06060429, 0.9999783, 0.9999783, 0.125007, 0.8750491, 0.7618897, 0.02380905, 0.2142815, 1.000077, 0.07777868, 0.7955648, 0.1177791, 0.008888992, 0.03846135, 0.09615337, 0.4743566, 0.2628192, 0.1282045, 0.2702727, 0.6891955, 0.05405455, 0.9999783, 0.1212136, 0.1212136, 0.2272754, 0.5151577, 0.1428637, 0.2142956, 0.03571593, 0.6071709, 0.9999688, 1.000013, 0.9999092, 1.000013, 1.000013, 0.4307942, 0.03118872, 0.07212392, 0.09551546, 0.3703661, 1.000077, 0.1724204, 0.05172613, 0.1206943, 0.5345033, 0.1034523, 1.000029, 1.000029, 1.000029, 0.9999092, 1.000029, 1.000013, 1.000031, 0.2584257, 0.08988722, 0.2471898, 0.0224718, 0.3258412, 0.05617951, 0.03750211, 0.2250126, 0.07500421, 0.6750379, 1.000077, 0.03409115, 0.443185, 0.1363646, 0.2613655, 0.1250009, 0.05263264, 0.5789591, 0.1754421, 0.1929864, 0.9999783, 0.9999092, 1.000029, 0.9999659, 0.115385, 0.3557703, 0.1538466, 0.09615413, 0.1250004, 0.1442312, 0.06153676, 0.5076782, 0.04615257, 0.3692205, 0.01538419, 0.03418913, 0.393175, 0.08547283, 0.09402012, 0.3333441, 0.0512837, 0.8214003, 0.1071392, 0.07142611, 0.9999092, 0.7599841, 0.03999916, 0.07999833, 0.03999916, 0.07999833, 0.08823144, 0.3529258, 0.5587991, 1.000029, 0.2338755, 0.1693581, 0.1048407, 0.04838802, 0.1935521, 0.2500048, 1.000029, 0.2813987, 0.3131951, 0.04928452, 0.07472168, 0.06995221, 0.1144673, 0.09697921, 0.2689652, 0.04137927, 0.08275854, 0.1034482, 0.3172411, 0.08275854, 0.09655163, 0.9999092, 0.1379306, 0.6379288, 0.03448264, 0.05172396, 0.1379306, 0.9999092, 0.02816969, 0.2535272, 0.1549333, 0.02816969, 0.4647998, 0.07042421, 0.9999092, 1.000029, 0.9999092, 0.9999688, 1.000032, 1.000012, 1.000013, 0.9999783, 0.9999783, 1.000029, 0.07075526, 0.4551922, 0.03301912, 0.06839675, 0.07547228, 0.1367935, 0.1580201, 0.05618081, 0.03932657, 0.2471956, 0.2696679, 0.3876476, 0.004255481, 0.008510962, 0.1404309, 0.6978989, 0.1446864, 1.000029, 0.9999092, 0.2338297, 0.2686554, 0.1840787, 0.1442779, 0.1094522, 0.0447759, 0.0199004, 0.9999092, 1.000013, 0.9999092, 0.9999783, 0.02083292, 0.08333167, 0.1249975, 0.06249875, 0.7291521, 0.1000011, 0.7666748, 0.1666684, 0.1904818, 0.8095476, 1.000029, 0.9999774, 0.999976, 0.07142887, 0.6428598, 0.08163299, 0.1224495, 0.0408165, 0.0408165, 0.05222324, 0.3616943, 0.003868388, 0.2823923, 0.1315252, 0.007736777, 0.1586039, 0.9999092, 0.3108219, 0.027028, 0.04054199, 0.6216439, 1.000032, 0.6666795, 0.05555663, 0.05555663, 0.1111133, 0.08333494, 0.1188843, 0.2447617, 0.3706391, 0.02797277, 0.2307753, 0.9999783, 0.9999783, 0.1052613, 0.05263067, 0.07894601, 0.7631448, 1.000077, 0.6969566, 0.1212098, 0.09090738, 0.09090738, 0.9999688, 0.9999092, 0.507448, 0.492523, 0.05262761, 0.7894141, 0.1052552, 0.1578979, 0.7894895, 0.05263264, 0.9999092, 0.3845952, 0.1281984, 0.4871539, 0.9473422, 0.02631506, 0.02631506, 1.000032, 1.000077, 1.000032, 0.999917, 1.000077, 0.3600216, 0.6400384, 0.313043, 0.3043473, 0.008695638, 0.1217389, 0.2521735, 1.000032, 1.000032, 0.9999783, 0.6250125, 0.1470618, 0.07353089, 0.1470618, 0.007353089, 0.8027008, 0.0136051, 0.1020382, 0.0408153, 0.0136051, 0.0272102, 0.8571613, 0.1428602, 1.000032, 0.6341469, 0.02439027, 0.04878053, 0.2682929, 0.02439027, 0.9999783, 0.522521, 0.3513503, 0.03603593, 0.02702695, 0.06306287, 0.1304392, 0.6521959, 0.1739189, 0.06250103, 0.07639014, 0.03472279, 0.5763984, 0.09027926, 0.1597248, 1.000029, 0.8947434, 0.05263196, 0.05263196, 1.000013, 1.000032, 0.3765751, 0.1075929, 0.1518959, 0.07911243, 0.2816402, 0.9999688, 1.000032, 0.9999688, 1.000013, 0.9999092, 0.8055759, 0.1944493, 0.1764768, 0.05882559, 0.05882559, 0.08823838, 0.02941279, 0.5882559, 1.000077, 1.000032, 0.8750159, 0.1250023, 0.9411889, 0.05882431, 1.000029, 1.000013, 0.7333458, 0.2666712, 0.9999783, 0.9999111, 0.2619026, 0.376981, 0.2242045, 0.1329354, 0.003968221, 0.001984111, 0.9999783, 0.1902858, 0.3805715, 0.0850213, 0.08097267, 0.2469666, 0.008097267, 0.9999783, 0.1842091, 0.09868347, 0.2105247, 0.2434192, 0.006578898, 0.1776302, 0.07894678, 0.09091489, 0.818234, 0.3372083, 0.1627902, 0.1453484, 0.06976724, 0.01744181, 0.1279066, 0.1337205, 0.9999688, 1.000032, 1.000077, 1.000077, 1.000029, 0.1084347, 0.0361449, 0.5060286, 0.0963864, 0.2650626, 0.02702723, 0.1081089, 0.5135173, 0.3648676, 0.2205943, 0.1764754, 0.102944, 0.4853074, 0.08510649, 0.2127662, 0.1276597, 0.5106389, 0.08510649, 0.121214, 0.09091049, 0.7878909, 1.000077, 1.000032, 0.09999771, 0.1545419, 0.1272698, 0.1727233, 0.4545351, 0.9999092, 0.04545353, 0.9545242, 0.888857, 0.1111071, 0.9999783, 0.9000019, 0.1000002, 1.000077, 1.000029, 0.7323989, 0.09859216, 0.1830997, 0.9999783, 0.6250139, 0.1250028, 0.09375208, 0.1250028, 1.000077, 1.000029, 0.9999688, 0.1785814, 0.6786094, 0.1428651, 0.0612274, 0.04081827, 0.3265461, 0.5714557, 0.6476607, 0.03885964, 0.2720175, 0.03885964, 1.000032, 0.9999688, 0.1904794, 0.09523972, 0.111113, 0.4285788, 0.1746062, 0.9999688, 0.2044444, 0.3377777, 0.2222222, 0.0622222, 0.08444442, 0.08888886, 0.9999092, 1.000013, 0.1851791, 0.03703582, 0.7777523, 0.06060533, 0.272724, 0.6666586, 1.000032, 1.000029, 1.000032, 0.04761875, 0.1428562, 0.04761875,   0.7619, 0.2032473, 0.1138185, 0.09755871, 0.1951174, 0.09755871, 0.2845462, 1.000029, 0.0828739, 0.7734897, 0.06077419, 0.01104985, 0.04972434, 0.02209971, 0.1100923, 0.3211026, 0.01834872, 0.3669744, 0.1743128, 1.000029, 1.000013, 1.000029, 1.000032, 0.9999688, 1.000032, 0.009971331, 0.1837574, 0.4273428, 0.3717882, 0.004273428, 0.001424476, 0.9999783, 0.9999688, 0.9999783, 0.9999783, 1.000077, 1.000077, 1.000077, 0.9999688, 1.000032, 0.03333381, 0.2476226, 0.05238171, 0.1904789, 0.1523831, 0.3238142, 1.000013, 0.0384623, 0.6923214, 0.0384623, 0.2307738, 0.3703691, 0.6296275, 0.9999093, 0.6616106, 0.01010093, 0.2828259, 0.0404037, 0.1726186, 0.130952, 0.1488091, 0.07142837, 0.2559516, 0.2202375, 1.000077, 0.2567697, 0.7432806, 0.9999688, 1.000077, 1.000029, 1.000029, 1.000032, 0.9999688, 0.2461657, 0.1076975, 0.09231214, 0.5077168, 0.03077071, 0.9999783, 0.9999688, 1.000032, 0.8662974, 0.001052609, 0.08947178, 0.04315698, 1.000013, 1.000032, 0.9999688, 0.8099789, 0.01999948, 0.06999818, 0.07999792, 0.02999922, 0.2105373, 0.1052687, 0.6842463, 0.9999092, 0.9999092, 0.9999783, 1.000032, 0.3333355, 0.09803985, 0.3333355, 0.0653599, 0.1699357, 0.8888579, 0.1111072, 0.8437667, 0.1562531, 0.9999092, 0.9999688, 0.07142809, 0.2499983, 0.6785669, 1.000077, 0.1428602, 0.04762007, 0.8095412, 0.01621659, 0.9243457, 0.06486636, 0.9999705, 0.07142719, 0.9285535, 1.000077, 0.9999688, 0.07999752, 0.3999876, 0.03999876, 0.4099873, 0.06499798, 0.004999845, 0.8332673, 0.1666535, 0.07407628, 0.9259535, 0.9999688, 0.2279299, 0.08829719, 0.1026711, 0.01642738, 0.2587313, 0.2053423, 0.1006177, 1.000029, 0.6034538, 0.3965553, 0.1249951, 0.1249951, 0.03124878, 0.5312292, 0.06249756, 0.09374633,   0.2143, 0.7857667, 0.9999688, 0.07207305, 0.2792831, 0.02702739, 0.07207305, 0.2342374, 0.1801826, 0.135137, 0.9999688, 0.9999783, 0.08695489, 0.9130264, 0.06666848, 0.6555734, 0.02222283, 0.2555625, 0.07692172, 0.1923043, 0.7307564, 0.03012036, 0.2409629, 0.09638515, 0.1987944, 0.246987, 0.06024072, 0.1265055, 0.9999094, 0.1818119, 0.0209783,  0.32866, 0.4405443, 0.02797106, 0.1016034, 0.2753988, 0.2834201, 0.2406397, 0.06951814, 0.02941152, 0.240001, 0.5200022, 0.06000025, 0.06000025, 0.1200005, 0.1450755, 0.2331571, 0.134713, 0.1658006, 0.07771902, 0.2383383, 0.2205103, 0.07179404, 0.1179474, 0.2666636, 0.01538444, 0.2153821, 0.08717848, 1.000013, 0.05633887, 0.09859303, 0.01408472, 0.4788804, 0.1126777, 0.2394402, 0.9999783, 0.136356, 0.2272601, 0.6514789, 0.9999688, 0.09756228, 0.07317171, 0.09756228, 0.09756228, 0.5365926, 0.09756228, 1.000029, 1.000013, 0.9999092, 0.9999688, 0.03846259, 0.07692517, 0.8077143, 0.07692517, 0.1818135, 0.2207735, 0.02597336, 0.402587, 0.01298668, 0.1558401, 1.000013, 0.3158078, 0.02631732, 0.6316156, 0.05263463, 0.1442285, 0.1442285, 0.2596112, 0.3076874, 0.04807615, 0.06730661, 0.01923046, 0.1710475, 0.2039412, 0.3684099, 0.2565712, 0.3275793, 0.3275793, 0.03448204, 0.04310254, 0.2672358, 1.000013, 0.1500102, 0.8500579, 0.05000341, 1.000029, 1.000032, 0.2499993, 0.190298, 0.3022379, 0.1604473, 0.007462665, 0.09328331, 1.000029, 0.558133, 0.2325554, 0.1395332, 0.06976662, 0.3636353, 0.6363617, 0.07376892, 0.2540929, 0.1721275, 0.3360584, 0.1229482, 0.03278618, 0.2077923, 0.05194807, 0.1298702, 0.1558442, 0.4025975, 0.05194807, 0.2121136, 0.03030195, 0.2794513, 0.4141266, 0.006733766, 0.06060389, 0.213904, 0.1122996, 0.347594, 0.1122996, 0.1390376, 0.0320856, 0.0374332, 0.9999092, 0.1929839, 0.1578959, 0.6491275, 0.3333383, 0.01515174, 0.03030348, 0.09091043, 0.4394004, 0.09091043, 0.7619118, 0.1904779, 0.04761949, 1.000013, 1.000029, 0.1111179, 0.8889435, 1.000029, 0.9999783, 0.9999688, 0.6666609, 0.03999966, 0.03999966, 0.05333287, 0.1733318, 0.02666644, 1.000029, 0.09090974, 0.04545487, 0.3181841, 0.5454585, 0.2889059, 0.7111529, 0.8666442, 0.1333299, 1.000032, 0.05128355, 0.9231039, 0.02564177, 1.000077, 1.000013, 0.02255716, 0.142862, 0.6541578, 0.1879764, 1.000029, 0.0595259, 0.1904829, 0.1428622, 0.3571554, 0.2500088, 0.3026328, 0.06578975, 0.5723708, 0.05921077, 0.9999783, 0.01234608, 0.01234608, 0.5802656, 0.2592676, 0.1358068, 1.000029, 1.000077, 1.000077, 0.9999783, 1.000013, 0.6896454, 0.03448227, 0.1034468, 0.1034468, 1.000013, 1.000013, 0.338617, 0.1587267, 0.08465424, 0.00529089, 0.4126894, 1.000077, 0.9999783, 0.9999092, 0.06023991, 0.03614394, 0.3674634, 0.2951755, 0.08433587, 0.1566238, 0.9999092, 0.9999092, 0.9999688, 0.9999688, 1.000029, 0.02732292, 0.2950875, 0.3060167, 0.08743333, 0.1584729, 0.1256854, 1.000077, 0.1481502, 0.02777816, 0.6666757, 0.09259385, 0.0648157, 0.9999092, 1.000013, 1.000013, 0.222223, 0.1367526, 0.07692333, 0.1794878, 0.06837629, 0.3162404, 0.9321773, 0.03389736, 0.05084604, 1.000032, 1.000032, 0.5624833, 0.0729145, 0.1354126, 0.1874944, 0.02083271, 0.02083271, 0.205361, 0.02678622, 0.205361, 0.01785748, 0.5446531, 0.09999715, 0.8999744, 0.8999775, 0.09999751, 0.1000044, 0.1333392, 0.1000044, 0.6666961, 1.000029, 0.02380742, 0.9761043, 0.3370779, 0.5056169, 0.07865152, 0.02247186, 0.05617965, 0.8571425, 0.1428571, 0.9999092, 0.2333314, 0.1619035, 0.1666653, 0.1404751, 0.09999919, 0.05952333, 0.1380941, 0.9999783, 0.9999688, 0.2063504, 0.1190483, 0.1031752, 0.2142869, 0.08730209, 0.2698428, 1.000032, 1.000077, 0.9999092, 0.3262993, 0.6736502, 0.3610946, 0.6388597, 1.000029, 1.000032, 1.000032, 1.000013, 0.1111121, 0.8888967, 0.1199959, 0.07999728, 0.01999932, 0.2199925, 0.559981, 1.000013, 1.000013 ] 
},
"R":       30,
"lambda.step":      0.1,
"plot.opts": {
 "xlab": "PC1",
"ylab": "PC2" 
},
"topic.order": [ 3, 4, 5, 7, 6, 1, 2 ] 
}