{
 "mdsDat": {
 "x": [ -0.03785368, -0.19705, -0.004973457, -0.06581497, 0.1050944, 0.2005977 ],
"y": [ 0.1370188, -0.08799267, 0.02884472, -0.05287799, 0.1096871, -0.1346799 ],
"topics": [ 1, 2, 3, 4, 5, 6 ],
"Freq": [ 20.61547, 19.99602, 17.24396, 17.00816, 12.82771, 12.30868 ],
"cluster": [        1,        1,        1,        1,        1,        1 ] 
},
"tinfo": {
 "Term": [ "offset", "wetland", "biodivers", "compens", "mitig", "bank", "market", "ecosystem", "stream", "permit", "ecolog", "conserv", "marin", "servic", "govern", "measur", "impact", "function", "plan", "environment", "speci", "nnl", "eia", "polici", "net", "avail", "regul", "site", "loss", "practic", "nnl", "multipli", "africa", "avert", "abstract", "currenc", "draft", "peru", "behalf", "colombia", "lend", "like--lik", "peer-review", "simul", "tree", "undesir", "licenc", "affair", "science-bas", "—", "academi", "argentina", "confid", "consum", "fauna", "fourth", "hundr", "induc", "multin", "national-level", "corp", "armi", "watersh", "permitte", "aco", "district", "flow", "hadd", "epa", "francisco", "nationwid", "pennsylvania", "intens", "passag", "riparian", "age", "creek", "discharg", "estuarin", "geomorph", "index", "palustrin", "perenni", "reestablish", "januari", "michigan", "ohio", "revis", "riverin", "affluent", "eia", "dutch", "hea", "energi", "netherland", "german", "rout", "sweden", "coher", "railway", "spain", "ant", "non-compli", "confus", "iaia", "scope", "fair", "accident", "bypass", "confirm", "consent", "greenfield", "perfect", "reinforc", "relianc", "solid", "spanish", "stewardship", "switzerland", "wild", "safetea-lu", "dredg", "ilf", "templat", "island", "proactiv", "remot", "korea", "usfw", "master", "owner", "project--project", "safe", "save", "staff", "statewid", "add", "biologist", "complement", "densiti", "diego", "facil", "ministri", "rancher", "reput", "underway", "mangrov", "conjunct", "straightforward", "piecem", "deforest", "eco-compens", "financ", "contract", "biobank", "bycatch", "volunt", "landhold", "neoliberalis", "palm", "aichi", "see", "abroad", "counter", "disput", "gerai", "incom", "india", "massiv", "mina", "preexist", "rescal", "saiga", "ambatovi", "avenu", "madagascar", "momentum", "overlap", "realign", "satellit", "avail", "geographi", "entri", "ontolog", "cap--trad", "eas", "economist", "intensifi", "mobil", "obscur", "reconfigur", "sale", "standardis", "dioxid", "spread", "automat", "cardiff", "deploy", "entail", "moreov", "nineteenth", "optim", "problemat", "theoriz", "treat", "wealth", "etc", "enter", "commod", "phenomenon", "offset", "biodivers", "licens", "franc", "leakag", "revers", "indirect", "metric", "quantif", "outcom", "hierarchi", "turtl", "french", "migratori", "african", "via", "australian", "iii", "captur", "stream", "permit", "wetland", "section", "san", "plant", "higher", "freshwat", "distanc", "engin", "chicago", "marin", "compens", "farmer", "germani", "measur", "great", "renew", "hydropow", "provinci", "european", "pursu", "unexpect", "halt", "fee", "-lieu", "colorado", "landown", "phase", "endang", "transport", "sens", "streamlin", "bank", "parcel", "updat", "alon", "suppli", "coastal", "england", "china", "programm", "hand", "bdo", "organis", "era", "market", "scienc", "banker", "geograph", "servic", "capit", "discours", "entrepreneuri", "ecosystem", "match", "polit", "except", "mbis", "skill", "extens", "emerald", "gain", "transpar", "commit", "gap", "net", "achiev", "flexibl", "mitig", "function", "water", "complianc", "qualiti", "site", "success", "canada", "compensatori", "fish", "less", "percent", "acreag", "ecolog", "principl", "sustain", "direct", "advers", "swedish", "infrastructur", "road", "agenc", "advanc", "speci", "plan", "delay", "program", "frame", "cost", "convent", "brazil", "wale", "transact", "form", "market-bas", "neoliber", "arena", "commodif", "translat", "hybrid", "ration", "loss", "challeng", "develop", "conserv", "implement", "calcul", "south", "restor", "impact", "requir", "result", "area", "project", "record", "develop", "environ", "environment", "impact", "legal", "avoid", "mitig", "conserv", "protect", "land", "credit", "regulatori", "feder", "usa", "wetland", "govern", "restrict", "right", "interview", "respons", "relev", "social", "legisl", "econom", "govern", "regul", "institut", "implic", "argu", "earli", "materi", "actor", "polici", "countri", "tool", "impact", "clear", "time", "loss", "type", "data", "net", "project", "plan", "implement", "practic", "damag", "manag", "propos", "habitat", "environment", "manag", "provid", "financi", "includ", "organ", "biodivers", "influenc", "local", "australia", "fisheri", "polici", "natur", "ecolog", "practic", "limit", "social", "decis", "use", "requir", "mine", "consid", "biolog", "state", "habitat", "natur", "paper", "develop", "process", "use", "state", "region", "conserv", "analysi", "institut", "case", "scheme", "environment", "differ", "bank", "area", "speci", "can", "support", "identifi", "studi", "monitor", "habitat", "effect", "assess", "use", "approach", "project", "nation", "polici", "environment", "case", "may", "function", "habitat", "site", "practic", "increas", "design", "use", "compens", "assess", "mitig", "polici", "offset", "paper", "develop", "forest", "use", "restor", "valu", "assess", "provid", "environment", "evalu", "effect", "requir", "review", "studi", "project", "particular", "paper", "relat", "new", "regul", "polici", "can", "use", "show", "effect", "develop", "process", "approach", "mitig", "project", "process", "area", "compens", "differ" ],
"logprob": [       30,       29,       28,       27,       26,       25,       24,       23,       22,       21,       20,       19,       18,       17,       16,       15,       14,       13,       12,       11,       10,        9,        8,        7,        6,        5,        4,        3,        2,        1,  -4.8711,  -6.3374,  -6.5606,  -6.5606,  -6.6476,  -7.0995,  -7.0995,   -7.436,  -7.6592,  -7.6592,  -7.9468,  -7.9468,  -7.9468,  -7.9468,  -7.9468,  -7.9468,  -7.9468,  -7.9468,  -7.6592,  -8.3523,  -8.3523,  -8.3523,  -8.3523,  -8.3523,  -8.3523,  -8.3523,  -8.3523,  -8.3523,  -8.3523,  -8.3523,  -5.6477,  -5.8369,  -5.6138,  -6.8177,  -6.9355,  -6.9355,  -6.9355,  -6.9355,   -7.069,   -7.069,   -7.069,   -7.069,  -7.2232,  -7.2232,  -7.2232,  -7.4055,  -7.4055,  -7.4055,  -7.4055,  -7.4055,  -7.4055,  -7.4055,  -7.4055,  -7.4055,  -7.6287,  -7.6287,  -7.6287,  -7.6287,  -7.6287,  -7.9163,  -4.8415,  -6.3819,  -6.4689,  -6.6696,  -6.6696,  -6.9209,  -6.9209,  -6.9209,  -7.0751,  -7.0751,  -7.0751,  -7.2574,  -7.2574,  -7.4805,  -7.4805,  -7.4805,  -7.4805,  -7.7682,  -7.7682,  -7.7682,  -7.7682,  -7.7682,  -7.7682,  -7.7682,  -7.7682,  -7.7682,  -7.7682,  -7.7682,  -7.7682,  -7.7682,  -6.7737,  -6.9072,  -6.9072,  -6.9072,  -7.0613,  -7.0613,  -7.0613,  -7.2437,  -7.2437,  -7.4668,  -7.4668,  -7.4668,  -7.4668,  -7.4668,  -7.4668,  -7.4668,  -7.7545,  -7.7545,  -7.7545,  -7.7545,  -7.7545,  -7.7545,  -7.7545,  -7.7545,  -7.7545,  -7.7545,  -7.7545,  -7.7545,  -7.7545,  -7.7545,  -5.4354,  -5.5752,  -5.9318,  -6.0059,  -6.2683,   -6.625,   -6.625,  -6.7791,  -6.7791,  -6.7791,  -6.9615,  -6.9615,  -7.1846,  -7.1846,  -7.1846,  -7.1846,  -7.1846,  -7.1846,  -7.1846,  -7.1846,  -7.1846,  -7.1846,  -7.1846,  -7.4723,  -7.4723,  -7.4723,  -7.4723,  -7.4723,  -7.4723,  -7.4723,  -4.7456,  -6.9203,  -7.1435,  -7.1435,  -7.4312,  -7.4312,  -7.4312,  -7.4312,  -7.4312,  -7.4312,  -7.4312,  -7.4312,  -7.4312,  -7.4312,  -7.4312,  -7.8366,  -7.8366,  -7.8366,  -7.8366,  -7.8366,  -7.8366,  -7.8366,  -7.8366,  -7.8366,  -7.8366,  -7.8366,  -7.8366,  -6.9203,  -6.2272,  -7.4312,  -2.5432,   -2.963,  -6.5606,  -6.7491,  -6.8482,   -6.966,  -7.0997,  -6.1189,  -7.2539,  -4.9342,   -5.418,  -6.8313,  -6.9279,  -7.6592,  -7.6592,  -6.8442,  -6.3156,  -7.4701,   -6.848,  -4.1436,  -3.9597,  -2.7617,  -5.5023,  -6.7124,  -5.8387,  -6.9355,  -6.8414,  -7.2232,  -5.8148,  -7.1019,  -4.4848,  -3.1792,  -6.9209,  -6.3128,  -4.1681,  -6.0952,  -7.2574,  -6.1585,  -7.2722,  -5.4959,  -7.2756,  -7.4805,  -7.4805,  -6.0306,  -6.6559,  -6.7737,  -5.9098,  -6.9072,  -5.1805,  -5.3282,  -7.0614,  -6.3656,   -3.637,  -7.2437,  -7.2437,  -7.2437,  -6.3871,  -5.1502,  -5.5264,  -4.8908,  -5.9865,   -6.492,  -6.7791,  -6.7794,  -6.9615,  -3.7442,  -5.0825,  -5.9654,  -5.3077,  -4.2403,  -5.5581,  -6.3326,  -6.4562,  -3.6893,  -6.5839,  -4.8829,  -6.9203,  -6.9203,  -7.1435,  -6.1548,  -7.1592,  -4.7575,   -5.798,  -5.9026,  -6.1869,  -4.6534,  -5.0906,   -6.044,  -3.2255,  -4.5334,   -4.841,  -5.0893,  -5.2494,   -4.536,  -4.9123,  -6.0214,  -4.5687,  -5.7713,  -6.0494,  -6.1838,  -6.3095,  -3.6528,  -4.9946,  -5.0771,  -5.2797,  -6.3329,  -6.5199,  -5.5067,  -6.1317,   -4.809,  -5.4405,  -4.3378,  -4.3645,  -6.5803,  -4.5934,  -5.7375,   -4.706,  -6.1168,  -5.8482,  -6.1968,  -5.6812,  -5.3408,  -5.6915,  -5.5767,  -6.4095,  -6.7091,  -6.3634,  -6.7326,  -6.8631,  -4.1988,  -5.3624,  -4.0264,  -4.2567,  -4.6544,  -6.1382,  -6.0856,  -4.3483,  -4.0148,  -4.4319,  -4.7145,  -4.5095,  -4.2438,  -6.0914,   -3.803,  -5.1862,  -3.9968,  -4.0439,  -5.3977,  -5.1545,  -3.4679,  -3.8938,  -4.5595,  -4.9455,  -4.9944,  -4.9245,  -5.2248,  -5.8984,  -3.6584,  -4.5428,  -5.7397,   -5.369,  -5.5852,  -5.1641,  -5.7591,  -5.2985,   -5.483,  -4.5173,  -4.6005,  -4.5222,  -5.1108,  -5.8632,  -5.6537,  -6.0408,  -6.0538,  -5.8429,  -4.3085,  -5.6327,  -5.3504,  -4.4612,  -5.8252,  -5.5092,   -4.419,  -5.3234,  -5.0867,  -4.9011,  -4.3428,  -4.7462,  -4.7003,  -4.8228,  -5.5156,  -4.8162,  -5.3277,   -4.495,  -4.2181,  -4.7671,  -4.9085,   -5.903,  -5.1112,  -6.0567,  -3.9178,  -5.6473,  -5.2523,  -5.5303,  -5.8792,  -3.9155,  -4.5828,  -4.1251,  -4.5326,  -5.1999,  -5.3237,  -5.3372,  -4.6494,  -4.9713,  -5.8262,   -5.602,   -5.936,   -4.944,  -4.7125,  -4.9836,  -5.2263,  -4.2995,   -5.017,  -4.5995,  -5.0282,  -5.2879,  -4.2919,  -5.2149,  -5.3627,  -5.1453,   -5.516,  -4.2018,  -4.9802,  -4.4864,  -5.1013,  -5.1874,  -5.3434,  -5.6132,  -5.5695,  -5.0037,  -5.4494,  -4.9084,  -5.0952,  -5.1017,  -4.8391,  -5.1965,  -4.7731,  -5.3662,  -4.5484,  -4.6787,  -5.1027,  -5.1734,  -5.0759,  -5.1734,  -5.3628,  -5.3043,  -5.4112,  -5.5213,  -4.8665,  -4.9203,  -5.1697,   -4.727,  -4.9073,  -4.4931,  -5.2171,  -4.7889,  -5.6304,  -4.6855,  -4.8861,  -5.2018,  -5.3577,  -5.3942,  -5.2125,  -5.2665,   -5.237,  -5.1596,  -5.3336,   -5.283,  -5.1823,  -5.5559,  -5.1663,   -5.223,  -5.1452,  -5.3673,  -5.1686,  -5.2903,  -5.3799,  -5.5524,  -5.4776,  -5.0234,   -5.157,  -5.1617,  -5.4569,  -5.4909,  -5.3902,  -5.5098,  -5.5358,  -5.5458 ],
"loglift": [       30,       29,       28,       27,       26,       25,       24,       23,       22,       21,       20,       19,       18,       17,       16,       15,       14,       13,       12,       11,       10,        9,        8,        7,        6,        5,        4,        3,        2,        1,   1.5791,   1.5791,   1.5791,   1.5791,   1.5791,   1.5791,   1.5791,   1.5791,   1.5791,   1.5791,   1.5791,   1.5791,   1.5791,   1.5791,   1.5791,   1.5791,   1.5791,   1.5791,   1.5791,   1.5791,   1.5791,   1.5791,   1.5791,   1.5791,   1.5791,   1.5791,   1.5791,   1.5791,   1.5791,   1.5791,   1.6096,   1.6096,   1.6096,   1.6096,   1.6096,   1.6096,   1.6096,   1.6096,   1.6096,   1.6096,   1.6096,   1.6096,   1.6096,   1.6096,   1.6096,   1.6096,   1.6096,   1.6096,   1.6096,   1.6096,   1.6096,   1.6096,   1.6096,   1.6096,   1.6096,   1.6096,   1.6096,   1.6096,   1.6096,   1.6096,   1.7577,   1.7577,   1.7577,   1.7577,   1.7577,   1.7577,   1.7577,   1.7577,   1.7577,   1.7577,   1.7577,   1.7577,   1.7577,   1.7577,   1.7577,   1.7577,   1.7577,   1.7577,   1.7577,   1.7577,   1.7577,   1.7577,   1.7577,   1.7577,   1.7577,   1.7577,   1.7577,   1.7577,   1.7577,   1.7577,   1.7715,   1.7715,   1.7715,   1.7715,   1.7715,   1.7715,   1.7715,   1.7715,   1.7715,   1.7715,   1.7715,   1.7715,   1.7715,   1.7715,   1.7715,   1.7715,   1.7715,   1.7715,   1.7715,   1.7715,   1.7715,   1.7715,   1.7715,   1.7715,   1.7715,   1.7715,   1.7715,   1.7715,   1.7715,   1.7715,   2.0536,   2.0536,   2.0536,   2.0536,   2.0536,   2.0536,   2.0536,   2.0536,   2.0536,   2.0536,   2.0536,   2.0536,   2.0536,   2.0536,   2.0536,   2.0536,   2.0536,   2.0536,   2.0536,   2.0536,   2.0536,   2.0536,   2.0536,   2.0536,   2.0536,   2.0536,   2.0536,   2.0536,   2.0536,   2.0536,   2.0949,   2.0949,   2.0949,   2.0949,   2.0949,   2.0949,   2.0949,   2.0949,   2.0949,   2.0949,   2.0949,   2.0949,   2.0949,   2.0949,   2.0949,   2.0949,   2.0949,   2.0949,   2.0949,   2.0949,   2.0949,   2.0949,   2.0949,   2.0949,   2.0949,   2.0949,   2.0949,   2.0949,   2.0949,   2.0949,   1.4774,    1.359,   1.5791,   1.5729,   1.5791,   1.5791,    1.579,   1.4611,    1.579,   1.3209,   1.3564,   1.4907,   1.4994,   1.5791,   1.5791,   1.4778,   1.4186,    1.545,    1.474,   1.6058,   1.4944,   1.3089,   1.4847,   1.6096,     1.49,   1.6096,    1.586,   1.6096,   1.4424,   1.5768,   1.7577,   1.4895,   1.7577,   1.6727,   1.4326,    1.639,   1.7577,   1.6328,   1.7429,   1.5451,   1.7395,   1.7577,   1.7577,   1.7036,   1.7715,   1.7715,   1.6702,   1.7715,   1.5729,   1.5829,   1.7714,    1.694,   1.3818,   1.7715,   1.7715,   1.7714,   1.6725,   1.5231,   2.0536,   1.8835,   1.9989,    2.053,   2.0535,   2.0533,   2.0535,   2.0441,   2.0456,   2.0943,   2.0211,   1.8957,    2.022,   2.0949,    2.089,   1.7763,   2.0948,   1.8705,   2.0949,   2.0949,   2.0949,   1.9849,   2.0792,   1.1943,   1.3002,    1.288,   1.3467,   0.9213,   1.0122,   1.2484,   0.9314,    1.247,   1.3062,   1.3012,   1.3147,   1.1188,   1.1479,   1.4251,   1.0587,   1.3567,   1.3971,   1.3963,   1.4247,   1.1369,   1.4556,   1.3578,   1.3936,   1.5836,   1.6197,   1.3567,   1.4972,   1.4589,   1.5205,   1.1451,    1.101,   1.6463,    1.126,   1.8913,   1.5618,   1.8686,   1.7806,   1.8627,   1.6852,   1.7873,   1.8421,   1.7521,   1.9125,   1.9696,   1.8634,   1.9461,   1.9698,   0.7524,   0.9856,   0.3816,   0.4762,   0.5995,   1.2283,   1.1716,   0.8827,   0.5985,    0.746,   0.8538,   0.7585,   0.5696,   1.3552,   0.6049,   1.1479,   0.6019,   0.5694,   1.1493,   1.0392,    0.689,   0.8391,   1.0089,   1.1682,   1.1875,   1.0751,   1.1951,    1.394,   0.4122,    1.286,   1.6659,   1.4713,   1.5428,   1.3496,   1.5696,   1.3558,   1.4279,   1.3115,   1.2283,   1.1824,   1.4029,   1.7169,   1.6036,   1.7506,   1.7376,   1.6462,   0.3655,   0.9665,   0.7524,   0.1521,   1.0381,   0.8113,   0.5322,   0.9837,   0.8194,   0.6736,   0.4706,   0.7193,   0.5536,   0.6257,   1.0836,   0.6154,   0.9531,   0.5844,   0.3806,   0.6645,   0.6792,   1.3203,   0.7427,    1.349,   0.4042,   1.4508,   1.1826,    1.333,   1.5264,   0.7585,    1.072,   0.6646,   0.9159,   1.2503,   1.3306,   1.3171,   0.1404,   0.2065,   0.9697,   0.7321,    1.051,   0.6307,   0.3669,   0.6712,   0.6798,   0.1084,   0.6172,   0.1903,   0.5466,   0.7723,    0.441,   1.0152,    1.151,   0.8642,   1.1965,   0.3969,   1.0392,   0.5324,   0.1667,   0.2955,   0.3253,   0.6939,   0.6243,   0.5583,   0.9267,    0.171,   0.3995,   0.3812,  -0.0494,   0.4242,   0.0403,   0.7697,   0.1255,    -0.08,   0.9067,   0.8868,   0.7045,   -0.094,    0.292,   0.1442,   0.3156,   0.5183,  -0.0767,  -0.2516,   0.3132,  -0.5701,  -0.2333,  -0.4725,    0.689,  -0.3809,   1.2806,   0.1043,   0.3449,   0.8902,   0.1252,   0.1934,  -0.6138,    0.506,   0.2576,   0.0182,   0.6562,    0.279,  -0.3689,   1.0433,   0.7398,    0.913,   0.5816,   0.3373,  -0.4947,   0.3784,  -0.5901,    0.945,   0.0171,  -0.6155,   0.4771,    0.459,     -1.3,  -0.6775,    0.244,  -0.2419,  -0.8671,   0.4736 ],
"Freq": [      737,      701,      546,      386,      643,      271,      125,      173,      130,      175,      342,      362,       80,       88,      121,      152,      407,      126,      174,      414,      170,       64,       56,      383,      155,       43,      136,      143,      290,      176, 64.99874, 14.99971, 11.99977, 11.99977, 10.99979, 6.999864, 6.999864, 4.999903, 3.999922, 3.999922, 2.999942, 2.999942, 2.999942, 2.999942, 2.999942, 2.999942, 2.999942, 2.999942, 3.999922, 1.999961, 1.999961, 1.999961, 1.999961, 1.999961, 1.999961, 1.999961, 1.999961, 1.999961, 1.999961, 1.999961, 28.99932, 23.99944, 29.99929, 8.999788, 7.999812, 7.999812, 7.999812, 7.999812, 6.999835, 6.999835, 6.999835, 6.999835, 5.999859, 5.999859, 5.999859, 4.999882, 4.999882, 4.999882, 4.999882, 4.999882, 4.999882, 4.999882, 4.999882, 4.999882, 3.999906, 3.999906, 3.999906, 3.999906, 3.999906, 2.999929, 56.00198, 12.00042, 11.00039, 9.000318, 9.000318, 7.000248, 7.000248, 7.000248, 6.000212, 6.000212, 6.000212, 5.000177, 5.000177, 4.000141, 4.000141, 4.000141, 4.000141, 3.000106, 3.000106, 3.000106, 3.000106, 3.000106, 3.000106, 3.000106, 3.000106, 3.000106, 3.000106, 3.000106, 3.000106, 3.000106, 7.999894, 6.999907, 6.999907, 6.999907,  5.99992,  5.99992,  5.99992, 4.999934, 4.999934, 3.999947, 3.999947, 3.999947, 3.999947, 3.999947, 3.999947, 3.999947,  2.99996,  2.99996,  2.99996,  2.99996,  2.99996,  2.99996,  2.99996,  2.99996,  2.99996,  2.99996,  2.99996,  2.99996,  2.99996,  2.99996, 23.00257, 20.00223, 14.00156, 13.00145, 10.00112, 7.000781, 7.000781,  6.00067,  6.00067,  6.00067, 5.000558, 5.000558, 4.000446, 4.000446, 4.000446, 4.000446, 4.000446, 4.000446, 4.000446, 4.000446, 4.000446, 4.000446, 4.000446, 3.000335, 3.000335, 3.000335, 3.000335, 3.000335, 3.000335, 3.000335, 43.99663, 4.999617, 3.999693, 3.999693,  2.99977,  2.99977,  2.99977,  2.99977,  2.99977,  2.99977,  2.99977,  2.99977,  2.99977,  2.99977,  2.99977, 1.999847, 1.999847, 1.999847, 1.999847, 1.999847, 1.999847, 1.999847, 1.999847, 1.999847, 1.999847, 1.999847, 1.999847, 4.999617, 9.999233,  2.99977, 666.6335, 438.1147, 11.99977, 9.938114, 8.999825,  7.99971,    6.999, 18.66269, 5.998912, 61.01999, 37.61521, 9.153182, 8.310477, 3.999909,  3.99971, 9.036099, 15.33046, 4.832135, 9.001862, 130.4978, 156.8474,  519.676, 33.53685, 9.999765, 23.95537, 7.999719, 8.789564, 5.999859, 24.53459, 6.773391, 80.00283, 295.1927, 7.000233, 12.85879, 109.8153, 15.98567, 5.000177, 15.00518, 4.926788,  29.1056, 4.909847, 4.000141, 4.000141, 16.81869,  8.99988, 7.999894, 18.97824, 6.999907, 39.35316,  33.9516, 5.999719, 12.03059, 184.2129, 4.999934, 4.999916, 4.999603, 11.77455, 40.56381, 21.00234, 39.65268, 13.25678, 7.996408, 6.000593, 5.999158, 5.000408, 119.7609, 31.41168, 12.99205, 25.07885, 72.92453, 19.52218, 8.999307, 7.952373, 126.5262, 6.999079, 38.35197, 4.999617, 4.999617, 3.999693, 10.75007, 3.937405,  72.8161,  25.7244, 23.16909, 17.43677, 80.80141, 52.18607, 20.11402, 326.8399, 88.37047, 64.96925, 50.68714, 43.18484, 88.14438, 60.50023, 19.95592, 85.30484, 25.62535, 19.40433, 16.96527, 14.96022, 183.8301, 48.05118, 44.24637, 36.13205,  12.6034, 10.45323, 28.79498, 15.41282, 57.06004, 30.34425, 91.40492, 88.99884, 9.706091, 70.79134, 17.00566, 47.70204, 11.63713, 15.22308, 10.74219,  17.9899, 24.26188, 17.08579, 19.16404, 8.332902, 6.175372, 8.726245,  6.03189, 5.294308, 127.3074, 39.76872, 151.2676, 120.1499, 80.72055, 18.30686, 19.29418, 106.3399, 148.4365, 97.81463, 73.73086,  90.5114, 118.0526, 18.60743, 158.1973, 39.67329, 130.3293, 124.3275, 32.10914, 40.94951, 218.1542, 142.4914, 73.23163,  49.7773, 47.40144, 50.83532, 37.64999, 19.19616, 180.3086, 56.16194, 16.96769, 24.58069, 19.80281,  30.1721, 16.64225, 26.37745, 21.93217, 55.28103, 50.86759, 55.00949, 30.53499,  14.3897, 17.74289, 12.04785, 11.89295, 14.68478, 114.0896,  30.3491, 40.24727, 97.92393,  25.0334, 34.33692, 99.07994, 40.10495, 50.81927, 61.18104, 92.20647, 61.60133, 64.49029, 57.05895, 28.53888, 57.43275, 34.43885, 78.10777, 103.0239, 59.49962, 51.65744,  19.1073, 42.17732, 16.38549,  104.924, 18.60996, 27.62409, 20.91971, 14.75754, 100.9094, 51.77716, 81.82255, 54.44241, 27.93187, 24.68072, 24.34827, 81.13207, 58.79933, 25.00894, 31.29346, 22.40781, 58.60981, 73.87963,  48.5822, 38.11442,  94.9708, 46.34455, 70.35826,  45.8296, 35.34493, 72.17408, 28.67691, 24.73659,   30.745,  21.2217, 75.78398, 34.79493, 57.01555, 51.63264, 47.37186, 40.52841, 30.94599, 32.32889, 55.21557, 35.35822, 52.37902, 43.45383, 43.16907, 56.13295, 39.26697, 59.14523, 32.68328, 55.84633,  49.0239, 30.78388, 28.68167, 31.61907,  48.0418, 39.75101, 42.14742, 37.87413, 33.92313,  63.3348, 60.01453, 46.77004,  62.7963, 51.71815, 59.02255, 28.61484, 43.90871, 18.92734,  46.7228, 38.22934, 27.87937, 39.95396, 38.52042, 46.19955, 42.45458, 43.72335,  40.7403, 33.76683, 26.78983, 29.62716,  20.3909, 28.88759, 27.29591, 29.50469, 38.38465, 40.37674, 35.26075, 24.31622, 20.46312, 22.05299, 33.32319, 29.15642, 29.02156, 36.18178, 34.97082,  32.3522, 21.35244, 20.80599,  20.5979 ],
"Total": [      737,      701,      546,      386,      643,      271,      125,      173,      130,      175,      342,      362,       80,       88,      121,      152,      407,      126,      174,      414,      170,       64,       56,      383,      155,       43,      136,      143,      290,      176, 64.99874, 14.99971, 11.99977, 11.99977, 10.99979, 6.999864, 6.999864, 4.999903, 3.999922, 3.999922, 2.999942, 2.999942, 2.999942, 2.999942, 2.999942, 2.999942, 2.999942, 2.999942, 3.999922, 1.999961, 1.999961, 1.999961, 1.999961, 1.999961, 1.999961, 1.999961, 1.999961, 1.999961, 1.999961, 1.999961, 28.99932, 23.99944, 29.99929, 8.999788, 7.999812, 7.999812, 7.999812, 7.999812, 6.999835, 6.999835, 6.999835, 6.999835, 5.999859, 5.999859, 5.999859, 4.999882, 4.999882, 4.999882, 4.999882, 4.999882, 4.999882, 4.999882, 4.999882, 4.999882, 3.999906, 3.999906, 3.999906, 3.999906, 3.999906, 2.999929, 56.00198, 12.00042, 11.00039, 9.000318, 9.000318, 7.000248, 7.000248, 7.000248, 6.000212, 6.000212, 6.000212, 5.000177, 5.000177, 4.000141, 4.000141, 4.000141, 4.000141, 3.000106, 3.000106, 3.000106, 3.000106, 3.000106, 3.000106, 3.000106, 3.000106, 3.000106, 3.000106, 3.000106, 3.000106, 3.000106, 7.999894, 6.999907, 6.999907, 6.999907,  5.99992,  5.99992,  5.99992, 4.999934, 4.999934, 3.999947, 3.999947, 3.999947, 3.999947, 3.999947, 3.999947, 3.999947,  2.99996,  2.99996,  2.99996,  2.99996,  2.99996,  2.99996,  2.99996,  2.99996,  2.99996,  2.99996,  2.99996,  2.99996,  2.99996,  2.99996, 23.00257, 20.00223, 14.00156, 13.00145, 10.00112, 7.000781, 7.000781,  6.00067,  6.00067,  6.00067, 5.000558, 5.000558, 4.000446, 4.000446, 4.000446, 4.000446, 4.000446, 4.000446, 4.000446, 4.000446, 4.000446, 4.000446, 4.000446, 3.000335, 3.000335, 3.000335, 3.000335, 3.000335, 3.000335, 3.000335, 43.99663, 4.999617, 3.999693, 3.999693,  2.99977,  2.99977,  2.99977,  2.99977,  2.99977,  2.99977,  2.99977,  2.99977,  2.99977,  2.99977,  2.99977, 1.999847, 1.999847, 1.999847, 1.999847, 1.999847, 1.999847, 1.999847, 1.999847, 1.999847, 1.999847, 1.999847, 1.999847, 4.999617, 9.999233,  2.99977, 737.9927,  546.003, 11.99977, 9.999809, 8.999825, 7.999844, 6.999864, 20.99976, 5.999883, 78.99868,  46.9996, 9.999757, 8.999882, 3.999922, 3.999922, 9.999802,       18, 4.999912, 9.999801, 130.9969, 175.9963, 701.9852, 37.99926, 9.999765, 26.99954, 7.999812,  8.99979, 5.999859, 28.99948, 6.999824, 80.00283, 386.0112, 7.000248, 14.00037, 152.0025, 18.00052, 5.000177, 17.00075, 5.000173,  36.0015, 5.000172, 4.000141, 4.000141, 17.99982, 8.999881, 7.999894, 20.99997, 6.999907, 47.99923, 40.99957,  5.99992, 12.99995, 271.9925, 4.999934, 4.999934, 4.999934, 12.99998, 51.99987, 21.00234, 47.00468, 14.00151, 8.000892,  6.00067, 6.000669, 5.000558, 125.9915, 32.99757,   12.999, 26.99804, 88.99433, 20.99856,  8.99931, 7.999389, 173.9897, 6.999463, 47.99814, 4.999617, 4.999617, 3.999693, 11.99922, 3.999705, 106.9985, 33.99963, 31.00012, 22.00015, 155.9973, 91.99869, 27.99965, 643.9909, 126.9958, 87.99747, 68.99846, 57.99785, 143.9974, 95.99951, 23.99967, 148.0004, 32.99929, 23.99948, 20.99958, 17.99961, 342.0004, 65.00128, 66.00368, 52.00078,  15.0004, 12.00034,  43.0008, 20.00044, 77.99907, 38.99968, 170.9967,  174.002, 10.99985, 134.9985, 20.00184, 78.00537, 14.00138, 20.00161, 13.00115, 26.00188, 32.99857, 21.99862,  26.9994, 9.999547, 6.999619, 10.99929, 6.999646, 5.999591, 290.9978, 71.99774, 501.0033, 362.0032,  215.001, 25.99938, 29.00071, 219.9951, 407.9997, 231.9985, 156.9997, 211.9996, 334.0023, 23.99959, 501.0033, 73.00183, 414.0018, 407.9997, 59.00189, 84.00095, 643.9909, 362.0032, 157.0011, 91.00096,  84.9973, 101.9973, 66.99893, 27.99973, 701.9852, 121.0026, 25.00186, 44.00292, 33.00245, 61.00298, 27.00176, 53.00112,  41.0028, 120.9979, 121.0026, 136.9952, 61.00062, 20.99886, 28.99905, 16.99901, 16.99918,  22.9998, 383.9965, 56.00024, 91.99824, 407.9997, 43.00004, 73.99906, 290.9978, 74.99857, 111.9986, 155.9973, 334.0023,  174.002,  215.001, 176.9985, 56.00046, 180.0022, 77.00046, 255.9982, 414.0018, 180.0022, 153.9984, 30.00078, 117.9999, 24.99951,  546.003, 34.00189, 66.00173,  43.0019, 25.00141, 383.9965, 143.9994, 342.0004, 176.9985, 64.99762, 53.00112, 52.99803, 341.9971, 231.9985, 46.00143, 72.99945, 37.99947, 155.9974, 255.9982, 143.9994, 112.0021, 501.0033, 146.9992, 341.9971, 155.9974, 95.99989, 362.0032, 81.00318, 61.00062, 101.0017,  50.0019, 414.0018, 99.99907, 271.9925, 211.9996, 170.9967, 141.9996, 74.99951, 83.99958, 158.0013, 69.99903, 255.9982, 169.0015, 170.9988, 341.9971,  148.999, 334.0023, 88.99972, 383.9965, 414.0018, 101.0017, 95.99908, 126.9958, 255.9982, 143.9974, 176.9985, 133.9986, 98.00014, 341.9971, 386.0112, 170.9988, 643.9909, 383.9965, 737.9927, 112.0021, 501.0033, 41.00169, 341.9971, 219.9951, 92.99884, 170.9988, 153.9984, 414.0018, 127.9997, 169.0015, 231.9985, 102.9997, 158.0013, 334.0023, 56.00092, 112.0021, 88.99833, 133.9994, 136.9952, 383.9965, 141.9996, 341.9971, 62.00239, 169.0015, 501.0033, 146.9992,  148.999, 643.9909, 334.0023, 146.9992, 211.9996, 386.0112, 99.99907 ],
"Category": [ "Default", "Default", "Default", "Default", "Default", "Default", "Default", "Default", "Default", "Default", "Default", "Default", "Default", "Default", "Default", "Default", "Default", "Default", "Default", "Default", "Default", "Default", "Default", "Default", "Default", "Default", "Default", "Default", "Default", "Default", "Topic1", "Topic1", "Topic1", "Topic1", "Topic1", "Topic1", "Topic1", "Topic1", "Topic1", "Topic1", "Topic1", "Topic1", "Topic1", "Topic1", "Topic1", "Topic1", "Topic1", "Topic1", "Topic1", "Topic1", "Topic1", "Topic1", "Topic1", "Topic1", "Topic1", "Topic1", "Topic1", "Topic1", "Topic1", "Topic1", "Topic2", "Topic2", "Topic2", "Topic2", "Topic2", "Topic2", "Topic2", "Topic2", "Topic2", "Topic2", "Topic2", "Topic2", "Topic2", "Topic2", "Topic2", "Topic2", "Topic2", "Topic2", "Topic2", "Topic2", "Topic2", "Topic2", "Topic2", "Topic2", "Topic2", "Topic2", "Topic2", "Topic2", "Topic2", "Topic2", "Topic3", "Topic3", "Topic3", "Topic3", "Topic3", "Topic3", "Topic3", "Topic3", "Topic3", "Topic3", "Topic3", "Topic3", "Topic3", "Topic3", "Topic3", "Topic3", "Topic3", "Topic3", "Topic3", "Topic3", "Topic3", "Topic3", "Topic3", "Topic3", "Topic3", "Topic3", "Topic3", "Topic3", "Topic3", "Topic3", "Topic4", "Topic4", "Topic4", "Topic4", "Topic4", "Topic4", "Topic4", "Topic4", "Topic4", "Topic4", "Topic4", "Topic4", "Topic4", "Topic4", "Topic4", "Topic4", "Topic4", "Topic4", "Topic4", "Topic4", "Topic4", "Topic4", "Topic4", "Topic4", "Topic4", "Topic4", "Topic4", "Topic4", "Topic4", "Topic4", "Topic5", "Topic5", "Topic5", "Topic5", "Topic5", "Topic5", "Topic5", "Topic5", "Topic5", "Topic5", "Topic5", "Topic5", "Topic5", "Topic5", "Topic5", "Topic5", "Topic5", "Topic5", "Topic5", "Topic5", "Topic5", "Topic5", "Topic5", "Topic5", "Topic5", "Topic5", "Topic5", "Topic5", "Topic5", "Topic5", "Topic6", "Topic6", "Topic6", "Topic6", "Topic6", "Topic6", "Topic6", "Topic6", "Topic6", "Topic6", "Topic6", "Topic6", "Topic6", "Topic6", "Topic6", "Topic6", "Topic6", "Topic6", "Topic6", "Topic6", "Topic6", "Topic6", "Topic6", "Topic6", "Topic6", "Topic6", "Topic6", "Topic6", "Topic6", "Topic6", "Topic1", "Topic1", "Topic1", "Topic1", "Topic1", "Topic1", "Topic1", "Topic1", "Topic1", "Topic1", "Topic1", "Topic1", "Topic1", "Topic1", "Topic1", "Topic1", "Topic1", "Topic1", "Topic1", "Topic2", "Topic2", "Topic2", "Topic2", "Topic2", "Topic2", "Topic2", "Topic2", "Topic2", "Topic2", "Topic2", "Topic3", "Topic3", "Topic3", "Topic3", "Topic3", "Topic3", "Topic3", "Topic3", "Topic3", "Topic3", "Topic3", "Topic3", "Topic3", "Topic4", "Topic4", "Topic4", "Topic4", "Topic4", "Topic4", "Topic4", "Topic4", "Topic4", "Topic4", "Topic4", "Topic4", "Topic4", "Topic4", "Topic4", "Topic5", "Topic5", "Topic5", "Topic5", "Topic5", "Topic5", "Topic5", "Topic6", "Topic6", "Topic6", "Topic6", "Topic6", "Topic6", "Topic6", "Topic6", "Topic6", "Topic6", "Topic6", "Topic6", "Topic6", "Topic6", "Topic6", "Topic6", "Topic1", "Topic1", "Topic1", "Topic1", "Topic1", "Topic1", "Topic1", "Topic2", "Topic2", "Topic2", "Topic2", "Topic2", "Topic2", "Topic2", "Topic2", "Topic2", "Topic2", "Topic2", "Topic2", "Topic2", "Topic3", "Topic3", "Topic3", "Topic3", "Topic3", "Topic3", "Topic3", "Topic3", "Topic4", "Topic4", "Topic4", "Topic4", "Topic4", "Topic4", "Topic5", "Topic5", "Topic5", "Topic5", "Topic5", "Topic5", "Topic6", "Topic6", "Topic6", "Topic6", "Topic6", "Topic6", "Topic6", "Topic6", "Topic1", "Topic1", "Topic1", "Topic1", "Topic1", "Topic1", "Topic1", "Topic2", "Topic2", "Topic2", "Topic2", "Topic2", "Topic2", "Topic2", "Topic3", "Topic3", "Topic3", "Topic3", "Topic3", "Topic3", "Topic4", "Topic4", "Topic4", "Topic4", "Topic4", "Topic4", "Topic4", "Topic4", "Topic4", "Topic5", "Topic5", "Topic5", "Topic5", "Topic5", "Topic5", "Topic5", "Topic5", "Topic6", "Topic6", "Topic6", "Topic6", "Topic6", "Topic6", "Topic6", "Topic6", "Topic6", "Topic1", "Topic1", "Topic1", "Topic1", "Topic1", "Topic1", "Topic2", "Topic2", "Topic2", "Topic2", "Topic3", "Topic3", "Topic3", "Topic3", "Topic3", "Topic3", "Topic3", "Topic4", "Topic4", "Topic4", "Topic4", "Topic4", "Topic4", "Topic4", "Topic5", "Topic5", "Topic5", "Topic5", "Topic5", "Topic6", "Topic6", "Topic6", "Topic6", "Topic6", "Topic6", "Topic6", "Topic1", "Topic1", "Topic1", "Topic1", "Topic1", "Topic2", "Topic2", "Topic3", "Topic3", "Topic4", "Topic4", "Topic4", "Topic4", "Topic4", "Topic5", "Topic5", "Topic5", "Topic5", "Topic5", "Topic6", "Topic6", "Topic6", "Topic1", "Topic1", "Topic1", "Topic1", "Topic1", "Topic2", "Topic2", "Topic3", "Topic3", "Topic3", "Topic3", "Topic3", "Topic4", "Topic4", "Topic5", "Topic5", "Topic6", "Topic6", "Topic6", "Topic1", "Topic1", "Topic1", "Topic1", "Topic1", "Topic2", "Topic2", "Topic2", "Topic3", "Topic4", "Topic5", "Topic5", "Topic5", "Topic5", "Topic6", "Topic6", "Topic6", "Topic1", "Topic1", "Topic1", "Topic2", "Topic2", "Topic3", "Topic4", "Topic5", "Topic5", "Topic5", "Topic6", "Topic6", "Topic6", "Topic2", "Topic3", "Topic4", "Topic5", "Topic5", "Topic5", "Topic6", "Topic6", "Topic6", "Topic1", "Topic1", "Topic3", "Topic5", "Topic5", "Topic5" ] 
},
"token.table": {
 "Term": [ "-lieu", "—", "abroad", "abstract", "academi", "accident", "achiev", "achiev", "achiev", "achiev", "achiev", "aco", "acreag", "acreag", "actor", "actor", "add", "advanc", "advanc", "advanc", "advers", "advers", "affair", "affluent", "africa", "african", "age", "agenc", "agenc", "agenc", "agenc", "agenc", "aichi", "alon", "ambatovi", "analysi", "analysi", "analysi", "analysi", "analysi", "ant", "approach", "approach", "approach", "approach", "approach", "approach", "area", "area", "area", "area", "area", "arena", "arena", "argentina", "argu", "argu", "argu", "argu", "armi", "assess", "assess", "assess", "assess", "assess", "assess", "australia", "australia", "australian", "australian", "automat", "avail", "avenu", "avert", "avoid", "avoid", "avoid", "avoid", "bank", "bank", "bank", "banker", "bdo", "behalf", "biobank", "biodivers", "biodivers", "biodivers", "biolog", "biolog", "biolog", "biolog", "biologist", "brazil", "brazil", "bycatch", "bypass", "calcul", "calcul", "calcul", "can", "can", "can", "can", "can", "can", "canada", "canada", "cap--trad", "capit", "capit", "captur", "captur", "cardiff", "case", "case", "case", "case", "case", "challeng", "challeng", "challeng", "chicago", "china", "china", "clear", "clear", "clear", "clear", "clear", "clear", "coastal", "coastal", "coher", "colombia", "colorado", "commit", "commit", "commit", "commit", "commod", "commodif", "commodif", "compens", "compens", "compens", "compens", "compensatori", "compensatori", "compensatori", "compensatori", "compensatori", "complement", "complianc", "complianc", "complianc", "confid", "confirm", "confus", "conjunct", "consent", "conserv", "conserv", "conserv", "conserv", "conserv", "consid", "consid", "consid", "consid", "consid", "consid", "consum", "contract", "convent", "convent", "corp", "cost", "cost", "cost", "cost", "cost", "counter", "countri", "countri", "countri", "countri", "countri", "credit", "credit", "credit", "creek", "currenc", "damag", "damag", "damag", "damag", "damag", "data", "data", "data", "data", "data", "data", "decis", "decis", "decis", "decis", "decis", "deforest", "delay", "delay", "densiti", "deploy", "design", "design", "design", "design", "design", "design", "develop", "develop", "develop", "develop", "develop", "develop", "diego", "differ", "differ", "differ", "differ", "differ", "differ", "dioxid", "direct", "direct", "direct", "direct", "discharg", "discours", "disput", "distanc", "district", "draft", "dredg", "dutch", "earli", "earli", "eas", "eco-compens", "ecolog", "ecolog", "ecolog", "ecolog", "ecolog", "ecolog", "econom", "econom", "econom", "econom", "econom", "economist", "ecosystem", "ecosystem", "ecosystem", "ecosystem", "ecosystem", "effect", "effect", "effect", "effect", "effect", "effect", "eia", "emerald", "endang", "endang", "endang", "endang", "endang", "energi", "engin", "engin", "engin", "england", "entail", "enter", "entrepreneuri", "entri", "environ", "environ", "environ", "environ", "environ", "environment", "environment", "environment", "environment", "environment", "environment", "epa", "era", "estuarin", "etc", "european", "european", "european", "evalu", "evalu", "evalu", "evalu", "evalu", "evalu", "except", "extens", "extens", "facil", "fair", "farmer", "fauna", "feder", "feder", "feder", "fee", "fee", "financ", "financi", "financi", "financi", "fish", "fish", "fish", "fisheri", "fisheri", "flexibl", "flexibl", "flexibl", "flow", "forest", "forest", "forest", "forest", "form", "form", "form", "form", "fourth", "frame", "frame", "franc", "francisco", "french", "freshwat", "function", "function", "function", "function", "gain", "gain", "gain", "gain", "gain", "gain", "gap", "gap", "geograph", "geograph", "geographi", "geomorph", "gerai", "german", "germani", "germani", "govern", "govern", "govern", "govern", "great", "great", "greenfield", "habitat", "habitat", "habitat", "habitat", "habitat", "habitat", "hadd", "halt", "hand", "hea", "hierarchi", "hierarchi", "higher", "hundr", "hybrid", "hybrid", "hydropow", "hydropow", "iaia", "identifi", "identifi", "identifi", "identifi", "identifi", "identifi", "iii", "ilf", "impact", "impact", "impact", "impact", "impact", "implement", "implement", "implement", "implement", "implement", "implement", "implic", "implic", "implic", "implic", "includ", "includ", "includ", "includ", "includ", "includ", "incom", "increas", "increas", "increas", "increas", "increas", "increas", "index", "india", "indirect", "induc", "influenc", "influenc", "influenc", "influenc", "influenc", "infrastructur", "infrastructur", "infrastructur", "institut", "institut", "institut", "intens", "intensifi", "interview", "interview", "interview", "island", "januari", "korea", "land", "land", "land", "land", "landhold", "landown", "landown", "leakag", "legal", "legal", "legal", "legal", "legisl", "legisl", "legisl", "legisl", "lend", "less", "less", "licenc", "licens", "like--lik", "limit", "limit", "limit", "limit", "limit", "local", "local", "local", "local", "local", "loss", "loss", "loss", "loss", "loss", "madagascar", "manag", "manag", "manag", "manag", "manag", "manag", "mangrov", "marin", "market", "market", "market-bas", "market-bas", "massiv", "master", "match", "materi", "materi", "materi", "may", "may", "may", "may", "may", "may", "mbis", "measur", "measur", "measur", "measur", "measur", "metric", "metric", "metric", "michigan", "migratori", "mina", "mine", "mine", "mine", "ministri", "mitig", "mitig", "mitig", "mitig", "mobil", "momentum", "monitor", "monitor", "monitor", "monitor", "monitor", "moreov", "multin", "multipli", "nation", "nation", "nation", "nation", "nation", "nation", "national-level", "nationwid", "natur", "natur", "natur", "natur", "natur", "natur", "neoliber", "neoliber", "neoliberalis", "net", "net", "net", "net", "netherland", "new", "new", "new", "new", "new", "new", "nineteenth", "nnl", "non-compli", "obscur", "offset", "offset", "offset", "ohio", "ontolog", "optim", "organ", "organ", "organ", "organis", "outcom", "outcom", "outcom", "outcom", "outcom", "outcom", "overlap", "owner", "palm", "palustrin", "paper", "paper", "paper", "paper", "parcel", "particular", "particular", "particular", "particular", "passag", "peer-review", "pennsylvania", "percent", "percent", "percent", "perenni", "perfect", "permit", "permit", "permit", "permit", "permitte", "peru", "phase", "phenomenon", "piecem", "plan", "plan", "plan", "plan", "plan", "plant", "plant", "polici", "polici", "polici", "polici", "polici", "polici", "polit", "polit", "practic", "practic", "practic", "practic", "practic", "practic", "preexist", "principl", "principl", "principl", "proactiv", "problemat", "process", "process", "process", "process", "process", "process", "program", "program", "program", "program", "program", "program", "programm", "programm", "project", "project", "project", "project", "project", "project--project", "propos", "propos", "propos", "propos", "propos", "propos", "protect", "protect", "protect", "protect", "protect", "protect", "provid", "provid", "provid", "provid", "provid", "provid", "provinci", "pursu", "qualiti", "qualiti", "quantif", "railway", "rancher", "ration", "ration", "realign", "reconfigur", "record", "record", "record", "reestablish", "region", "region", "region", "region", "region", "region", "regul", "regul", "regul", "regul", "regulatori", "regulatori", "regulatori", "regulatori", "regulatori", "regulatori", "reinforc", "relat", "relat", "relat", "relat", "relat", "relat", "relev", "relev", "relev", "relianc", "remot", "renew", "reput", "requir", "requir", "requir", "requir", "requir", "requir", "rescal", "respons", "respons", "respons", "respons", "respons", "restor", "restor", "restor", "restor", "restor", "restor", "restrict", "restrict", "restrict", "restrict", "result", "result", "result", "result", "result", "result", "revers", "review", "review", "review", "review", "review", "revis", "right", "right", "right", "right", "riparian", "riverin", "road", "road", "rout", "safe", "safetea-lu", "saiga", "sale", "san", "satellit", "save", "scheme", "scheme", "scheme", "scheme", "scheme", "scienc", "scienc", "science-bas", "scope", "section", "section", "section", "see", "sens", "servic", "servic", "servic", "servic", "show", "show", "show", "show", "show", "simul", "site", "site", "site", "site", "skill", "social", "social", "social", "solid", "south", "south", "spain", "spanish", "speci", "speci", "speci", "speci", "spread", "staff", "standardis", "state", "state", "state", "state", "state", "state", "statewid", "stewardship", "straightforward", "stream", "streamlin", "streamlin", "studi", "studi", "studi", "studi", "studi", "studi", "success", "success", "success", "success", "success", "suppli", "suppli", "support", "support", "support", "support", "support", "support", "sustain", "sustain", "sustain", "sweden", "swedish", "swedish", "switzerland", "templat", "theoriz", "time", "time", "time", "time", "time", "time", "tool", "tool", "tool", "tool", "tool", "transact", "transact", "transact", "translat", "translat", "transpar", "transpar", "transpar", "transport", "transport", "transport", "treat", "tree", "turtl", "turtl", "type", "type", "type", "type", "underway", "undesir", "unexpect", "updat", "usa", "usa", "usa", "usa", "use", "use", "use", "use", "use", "use", "usfw", "valu", "valu", "valu", "valu", "valu", "valu", "via", "via", "volunt", "wale", "wale", "water", "water", "water", "water", "water", "watersh", "wealth", "wetland", "wetland", "wetland", "wild" ],
"Topic": [ 4, 1, 5, 1, 1, 3, 1, 2, 3, 4, 5, 2, 2, 4, 5, 6, 4, 1, 3, 4, 1, 3, 1, 2, 1, 1, 2, 2, 3, 4, 5, 6, 5, 4, 5, 2, 3, 4, 5, 6, 3, 1, 2, 3, 4, 5, 6, 1, 2, 3, 4, 5, 5, 6, 1, 3, 4, 5, 6, 2, 1, 2, 3, 4, 5, 6, 1, 5, 1, 5, 6, 6, 5, 1, 1, 2, 3, 5, 2, 4, 6, 6, 5, 1, 5, 1, 5, 6, 1, 2, 4, 5, 4, 1, 5, 5, 3, 1, 3, 6, 1, 2, 3, 4, 5, 6, 2, 3, 6, 3, 6, 1, 2, 6, 2, 3, 4, 5, 6, 1, 4, 6, 2, 3, 5, 1, 2, 3, 4, 5, 6, 3, 4, 3, 1, 4, 1, 4, 5, 6, 6, 5, 6, 1, 2, 3, 5, 1, 2, 3, 4, 5, 4, 1, 2, 4, 1, 3, 3, 4, 3, 1, 3, 4, 5, 6, 1, 2, 3, 4, 5, 6, 1, 5, 3, 5, 2, 1, 2, 3, 4, 5, 5, 1, 3, 4, 5, 6, 1, 4, 6, 2, 1, 2, 3, 4, 5, 6, 1, 2, 3, 4, 5, 6, 1, 2, 3, 4, 6, 5, 1, 4, 4, 6, 1, 2, 3, 4, 5, 6, 1, 2, 3, 4, 5, 6, 4, 1, 2, 3, 4, 5, 6, 6, 1, 2, 3, 6, 2, 6, 5, 2, 2, 1, 4, 3, 4, 6, 6, 5, 1, 2, 3, 4, 5, 6, 1, 3, 4, 5, 6, 6, 1, 2, 3, 4, 6, 1, 2, 3, 4, 5, 6, 3, 6, 1, 2, 4, 5, 6, 3, 2, 3, 4, 5, 6, 6, 6, 6, 1, 3, 4, 5, 6, 1, 2, 3, 4, 5, 6, 2, 5, 2, 6, 2, 3, 5, 1, 2, 3, 4, 5, 6, 6, 3, 6, 4, 3, 3, 1, 2, 4, 5, 3, 4, 5, 3, 4, 5, 1, 2, 4, 2, 5, 1, 3, 4, 2, 1, 2, 4, 5, 3, 4, 5, 6, 1, 1, 5, 1, 2, 1, 2, 2, 3, 5, 6, 1, 2, 3, 4, 5, 6, 1, 5, 2, 6, 6, 2, 5, 3, 3, 6, 3, 4, 5, 6, 2, 3, 3, 1, 2, 3, 4, 5, 6, 2, 3, 5, 3, 1, 3, 2, 1, 5, 6, 3, 5, 3, 1, 2, 3, 4, 5, 6, 1, 4, 1, 2, 3, 4, 5, 1, 2, 3, 4, 5, 6, 1, 2, 3, 6, 1, 2, 3, 4, 5, 6, 5, 1, 2, 3, 4, 5, 6, 2, 5, 1, 1, 1, 3, 4, 5, 6, 1, 3, 4, 3, 5, 6, 2, 6, 3, 4, 5, 4, 2, 4, 2, 3, 4, 5, 5, 4, 5, 1, 2, 3, 4, 5, 3, 4, 5, 6, 1, 2, 4, 1, 1, 1, 1, 2, 3, 4, 6, 2, 3, 4, 5, 6, 1, 2, 3, 4, 5, 5, 1, 2, 3, 4, 5, 6, 4, 3, 5, 6, 4, 6, 5, 4, 6, 4, 5, 6, 1, 2, 3, 4, 5, 6, 6, 1, 2, 3, 4, 6, 1, 2, 5, 2, 1, 5, 1, 2, 5, 4, 1, 2, 3, 4, 6, 5, 1, 2, 3, 4, 5, 6, 1, 1, 1, 2, 3, 4, 5, 6, 1, 2, 1, 2, 3, 4, 5, 6, 5, 6, 5, 1, 2, 3, 4, 3, 1, 2, 3, 4, 5, 6, 6, 1, 3, 6, 1, 5, 6, 2, 6, 6, 1, 4, 6, 5, 1, 2, 3, 4, 5, 6, 5, 4, 5, 2, 3, 4, 5, 6, 4, 2, 3, 5, 6, 2, 1, 2, 1, 2, 3, 2, 3, 1, 2, 3, 4, 2, 1, 4, 6, 4, 1, 2, 3, 4, 5, 2, 3, 1, 2, 3, 4, 5, 6, 5, 6, 1, 2, 3, 4, 5, 6, 5, 1, 3, 6, 4, 6, 1, 2, 3, 4, 5, 6, 1, 2, 3, 4, 5, 6, 3, 5, 1, 2, 3, 4, 5, 4, 1, 2, 3, 4, 5, 6, 1, 2, 3, 4, 5, 6, 1, 2, 3, 4, 5, 6, 3, 3, 2, 6, 1, 3, 4, 4, 6, 5, 6, 2, 3, 4, 2, 1, 2, 3, 4, 5, 6, 2, 3, 4, 6, 1, 2, 3, 4, 5, 6, 3, 1, 2, 3, 4, 5, 6, 1, 3, 5, 3, 4, 3, 4, 1, 2, 3, 4, 5, 6, 5, 1, 2, 3, 4, 5, 1, 2, 3, 4, 5, 6, 3, 4, 5, 6, 1, 2, 3, 4, 5, 6, 1, 1, 2, 3, 4, 5, 2, 2, 3, 5, 6, 2, 2, 2, 3, 3, 4, 4, 5, 6, 2, 5, 4, 1, 3, 4, 5, 6, 4, 6, 1, 3, 2, 3, 4, 5, 4, 2, 3, 4, 6, 1, 2, 3, 5, 6, 1, 1, 2, 3, 4, 6, 3, 5, 6, 3, 1, 5, 3, 3, 1, 2, 4, 6, 6, 4, 6, 1, 2, 3, 4, 5, 6, 4, 3, 4, 2, 4, 5, 1, 2, 3, 4, 5, 6, 1, 2, 3, 4, 5, 4, 5, 1, 2, 3, 4, 5, 6, 3, 4, 5, 3, 1, 3, 3, 4, 6, 1, 2, 3, 4, 5, 6, 1, 3, 4, 5, 6, 2, 4, 5, 1, 6, 1, 3, 6, 2, 3, 4, 6, 1, 1, 6, 1, 2, 4, 5, 4, 1, 3, 4, 1, 2, 3, 4, 1, 2, 3, 4, 5, 6, 4, 1, 2, 3, 4, 5, 6, 1, 2, 5, 1, 5, 2, 3, 4, 5, 6, 2, 6, 2, 4, 6, 3 ],
"Freq": [ 1.000013, 1.000019, 0.9998884, 1.000019, 1.000019, 0.9999646, 0.5652255, 0.2826127, 0.0543486, 0.06521832, 0.02173944, 1.000024, 0.8333515, 0.1666703, 0.3478291, 0.6521795, 1.000013, 0.1025649, 0.1282062, 0.769237, 0.1333298, 0.8666436, 1.000019, 1.000024, 1.000019, 1.000019, 1.000024, 0.153848, 0.038462, 0.730778, 0.038462, 0.05128266, 0.9998884, 1.000013, 0.9998884, 0.1851779, 0.2839395, 0.123452, 0.3580107, 0.06172598, 0.9999646, 0.2147666, 0.04698019, 0.2617468, 0.221478, 0.0604031, 0.1946322, 0.2452835, 0.429246, 0.09905678, 0.1320757, 0.09905678, 0.2000091, 0.8000362, 1.000019, 0.1724195, 0.1379356, 0.1034517, 0.6207101, 1.000024, 0.2339197, 0.2748557, 0.2514637, 0.06432792, 0.05263193, 0.1228078, 0.5116052, 0.4883505, 0.8333334, 0.1666667, 1.000077, 1.000077, 0.9998884, 1.000019, 0.3571388, 0.1190463, 0.4880897, 0.03571388, 0.1139737, 0.6764893, 0.2095646, 1.000077, 0.9998884, 1.000019, 0.9998884, 0.8021935, 0.1923067, 0.005494476, 0.5789554, 0.1578969, 0.2105292, 0.02631616, 1.000013, 0.2499799, 0.7499398, 0.9998884, 0.9999646, 0.6923242, 0.1153874, 0.1923123, 0.2887332, 0.08450727, 0.1690145, 0.2464795, 0.09859182, 0.1197186, 0.8333447, 0.1666689, 1.000077, 0.04762232, 0.9524465, 0.9000179, 0.100002, 1.000077, 0.09900821, 0.2574214, 0.01980164, 0.3069255, 0.3069255, 0.555573, 0.2083399, 0.2361185, 1.000025, 0.1489213, 0.850979, 0.5813948, 0.06976738, 0.06976738, 0.09302317, 0.1395348, 0.04651158, 0.211539, 0.7884636, 0.9999646, 1.000019, 1.000013, 0.7419326, 0.06451588, 0.1935476, 0.03225794, 1.000077, 0.1428649, 0.8571896, 0.02590599, 0.1554359, 0.7642266, 0.05440257, 0.01351348, 0.5743229, 0.1216213, 0.1621618, 0.1283781, 1.000013, 0.2463823, 0.7391469, 0.01449308, 1.000019, 0.9999646, 0.9999646, 1.000013, 0.9999646, 0.3314888, 0.03591129, 0.3922618, 0.1988933, 0.03867369, 0.4246608, 0.1232886, 0.1917823, 0.1643848, 0.02739747, 0.05479494, 1.000019, 0.9998884, 0.142843, 0.8570582, 1.000024, 0.02563926, 0.02563926, 0.1281963, 0.2179337, 0.6153422, 0.9998884, 0.5357119, 0.1964277, 0.08928532, 0.1071424, 0.05357119, 0.1647111, 0.5529587, 0.2705968, 1.000024, 1.000019, 0.08928498, 0.5178529, 0.142856, 0.07142798, 0.196427, 0.1785737, 0.4553629, 0.04464343, 0.03571474, 0.1160729, 0.169645, 0.1320804, 0.2075549, 0.1698176, 0.01886863, 0.452847, 0.9998884, 0.09091036, 0.9091036, 1.000013, 1.000077, 0.3469383, 0.1326529, 0.1632651, 0.04081627, 0.1632651, 0.153061, 0.3013952, 0.0379239, 0.3153672, 0.1896195, 0.08782378, 0.06586783, 1.000013, 0.1600015, 0.1800017, 0.07000065, 0.04000037, 0.2100019, 0.3500032, 1.000077, 0.2115353, 0.03846096, 0.6922973, 0.05769144, 1.000024, 1.000077, 0.9998884, 1.000024, 1.000024, 1.000019, 1.000013, 0.9999646, 0.2941348, 0.7059234, 1.000077, 0.9998884, 0.09649112, 0.05263152, 0.5380111, 0.03508768, 0.03508768, 0.2397658, 0.1404983, 0.1404983, 0.1157045, 0.1570275, 0.4545532, 1.000077, 0.1609291, 0.05172721, 0.02873734, 0.02873734, 0.7299284, 0.1834304, 0.2603528, 0.2544357, 0.1242593, 0.1301764, 0.04733687, 0.9999646, 1.000074, 0.04166733, 0.02083367, 0.812513, 0.02083367, 0.08333467, 0.9999646, 0.8620845, 0.06896676, 0.06896676, 0.9998884, 1.000077, 1.000077, 1.000076, 1.000077, 0.1643794, 0.5479314, 0.1232846, 0.1232846, 0.05479314, 0.1111106, 0.02415449, 0.3140083, 0.2487912, 0.118357, 0.1835741, 1.000024, 0.9998884, 1.000024, 1.000077, 0.05555325, 0.8055221, 0.1388831, 0.2656256, 0.3281257, 0.1953129, 0.1171878, 0.06250014, 0.02343755, 1.000077, 0.08333875, 0.9167263, 1.000013, 0.9999646, 0.9999646, 1.000019, 0.4179171, 0.5671733, 0.01492561, 0.05555612, 0.944454, 0.9998884, 0.06666494, 0.6333169, 0.2666598, 0.06060737, 0.7878958, 0.1515184, 0.3999775, 0.5999663, 0.7142948, 0.1071442, 0.1785737, 1.000024, 0.09755696, 0.2438924, 0.1951139, 0.4633956, 0.1212174, 0.06060869, 0.09091304, 0.7273043, 1.000019, 0.1499862, 0.8499218, 1.000019, 1.000024, 0.8889006, 1.000023, 0.6929361, 0.04724565, 0.007874274, 0.2519768, 0.6822523, 0.1869184, 0.04672961, 0.02803777, 0.03738369, 0.01869184, 0.7727221, 0.181817, 0.03703973, 0.9259933, 1.000077, 1.000024, 0.9998884, 0.9999646, 0.9285471, 0.0714267, 0.07437854, 0.03305713, 0.4627998, 0.4214784, 0.1111079, 0.8888633, 0.9999646, 0.1875013, 0.2890645, 0.2031264, 0.3046896, 0.007812555, 0.007812555, 1.000024, 0.9999646, 0.9998885, 0.9999646, 0.8085176, 0.191491, 1.000024, 1.000019, 0.1428644, 0.8571863, 0.8823138, 0.1176418, 0.9999646, 0.3809543, 0.08333375, 0.2261916, 0.2738109, 0.01190482, 0.02380964, 1.000018, 1.000013, 0.2401962, 0.3627453, 0.3039218, 0.06617651, 0.02450982, 0.3767425, 0.04186027, 0.2976731, 0.1348831, 0.08372055, 0.06976712, 0.1904865, 0.04762162, 0.09524325, 0.6667027,  0.20339, 0.1864408, 0.1186442, 0.3559325, 0.09322042, 0.03389834, 0.9998884, 0.283585, 0.2164201, 0.2014946, 0.1343297, 0.04477658, 0.126867, 1.000024, 0.9998884, 1.000019, 1.000019, 0.1764608, 0.1470506, 0.05882026, 0.5587925, 0.08823039, 0.1162769, 0.674406, 0.2325538, 0.09835965, 0.4098319, 0.5081915, 1.000024, 1.000077, 0.272707, 0.1515039, 0.6060155, 1.000013, 1.000024, 1.000013, 0.09890006, 0.2527446, 0.5494448, 0.09890006, 0.9998884, 0.904763, 0.09523821, 1.000019, 0.03389722, 0.5423555, 0.2711777, 0.1525375, 0.3414401, 0.09755432, 0.5365488, 0.02438858, 1.000019, 0.7916837, 0.2083378, 1.000019, 1.000019, 1.000019, 0.1230814, 0.1076963, 0.1230814, 0.2153925, 0.430785, 0.1666623, 0.06060447, 0.1363601, 0.4242313, 0.2272668, 0.4364294, 0.3402088, 0.1099665, 0.06185614, 0.05498323, 0.9998884, 0.07222134, 0.1444427, 0.3166628, 0.3277738, 0.1111098, 0.02777744, 1.000013, 0.9999646, 0.04762226, 0.9524451, 0.2272869, 0.7727756, 0.9998884, 1.000013, 1.000077, 0.2353055, 0.05882636, 0.7059164, 0.1562515, 0.1145844, 0.0625006, 0.1875018, 0.177085, 0.3020862, 1.000077, 0.1184191, 0.08552491, 0.7236723, 0.01973652, 0.05920955, 0.9047724, 0.0476196, 0.0476196, 1.000024, 1.000019, 0.9998884, 0.5434613, 0.06521536, 0.3912922, 1.000013, 0.05590141, 0.5077711, 0.09782746, 0.3385141, 1.000077, 0.9998884, 0.3571478, 0.5000069, 0.08571547, 0.02857182, 0.02857182, 1.000077, 1.000019, 1.000019, 0.1460679, 0.05617995, 0.2134838, 0.3707877, 0.07865194, 0.1348319, 1.000019, 1.000024, 0.04166685, 0.06944475, 0.3402793, 0.06250027, 0.131945, 0.3611127, 0.2963028, 0.7037192, 0.9998884, 0.5192399, 0.3910325, 0.05769332, 0.03205185, 0.9999646, 0.1044781, 0.1492544, 0.2014935, 0.2014935, 0.1194036, 0.2238817, 1.000077, 1.000019, 0.9999646, 1.000077, 0.903803, 0.07994659, 0.01626032, 1.000024, 1.000077, 1.000077, 0.2800055, 0.6400125, 0.08000156, 0.9998885, 0.7721648, 0.02531688, 0.01265844, 0.03797532, 0.05063376, 0.08860908, 0.9998884, 1.000013, 0.9998884, 1.000024, 0.3392793, 0.1428545, 0.2589237, 0.2589237, 1.000013, 0.08928425, 0.1785685, 0.357137, 0.3749938, 1.000024, 1.000019, 1.000024,  0.14286,  0.80954,  0.04762, 1.000024, 0.9999646, 0.01704581, 0.8920641, 0.03409162, 0.0625013, 1.000024, 1.000019, 1.000013, 1.000077, 1.000013, 0.04022941, 0.02298824, 0.3563176, 0.5114882, 0.06896471, 0.8889039, 0.111113, 0.2968777, 0.054688, 0.1041676, 0.1354179, 0.1458347, 0.2630232, 0.2083414, 0.7916974, 0.2372901, 0.03954835, 0.3220366, 0.005649764, 0.08474647, 0.3050873, 0.9998884, 0.2307647, 0.738447, 0.03076863, 1.000013, 1.000077, 0.09523864, 0.08163312, 0.2176883, 0.312927, 0.08843588,  0.19728, 0.1185199, 0.2740772, 0.02222247, 0.5259319, 0.04444495, 0.01481498, 0.07142089, 0.9284716, 0.1047897, 0.353291, 0.2754472, 0.1766455, 0.08981973, 1.000013, 0.3376603, 0.1168824, 0.4415558, 0.0389608, 0.01298693, 0.02597387, 0.1401264, 0.07643261, 0.165604, 0.464965, 0.1210183, 0.03184692, 0.2532493, 0.1753265, 0.03246786, 0.3376658, 0.09740359, 0.1103907, 0.9999654, 0.9999656, 0.7414068, 0.2586303, 1.000019, 0.9999646, 1.000013, 0.166678, 0.8333902, 0.9998884, 1.000077,  0.79168, 0.08333474, 0.1250021, 1.000024, 0.1354168, 0.2500003, 0.1145835, 0.3645838, 0.1041668, 0.03125004, 0.277382, 0.1313915, 0.1824881, 0.4014739, 0.02941255, 0.2549088, 0.009804183, 0.5000133, 0.01960837, 0.2058878, 0.9999646, 0.1910148, 0.1235978, 0.2584318, 0.1011255, 0.0337085, 0.3033765, 0.296277, 0.07406925, 0.6295886, 0.9999646, 1.000013, 0.9999646, 1.000013, 0.254312, 0.4224166, 0.1767253, 0.07327635, 0.04741411, 0.03017262, 0.9998884, 0.08196321, 0.1967117, 0.06557057, 0.1639264, 0.4917793, 0.1045478, 0.4818289, 0.06363778, 0.1363667, 0.03636444, 0.1727311, 0.1199911, 0.1599881, 0.6799494, 0.03999702, 0.1464971, 0.4713386, 0.1401277, 0.08917217, 0.1019111, 0.05095553, 1.000019, 0.2524278, 0.165049, 0.2330103, 0.3300979, 0.01941753, 1.000024, 0.1363546, 0.2727092, 0.5681442, 0.02272577, 1.000024, 1.000024, 0.2499945, 0.7499836, 0.9999646, 1.000013, 1.000013, 0.9998884, 1.000077, 1.000024, 0.9998884, 1.000013, 0.3399871, 0.1199954, 0.01999924, 0.4199841, 0.07999697, 0.06061052, 0.9394631, 1.000019, 0.9999646, 0.8947544, 0.05263261, 0.05263261, 0.9998884, 1.000013, 0.02247334, 0.03371001, 0.1236034, 0.820277, 0.1612841, 0.1935409, 0.3064398, 0.3225682, 0.01612841, 1.000019, 0.2777828, 0.6111222, 0.06250113, 0.04861199, 1.000077, 0.03773505, 0.4905557, 0.4716881, 0.9999646, 0.6551564, 0.3448192, 0.9999646, 0.9999646, 0.2748591, 0.1462016, 0.532174, 0.04678453, 1.000077, 1.000013, 1.000077, 0.04487255, 0.3782115, 0.05128292, 0.2948768, 0.07051401, 0.1666695, 1.000013, 0.9999646, 1.000013,  0.99239, 0.9230806, 0.07692338, 0.1202522, 0.3480984,  0.20253, 0.0822778, 0.1708847, 0.07594873, 0.1041672, 0.6354199, 0.03125016, 0.1250006, 0.1145839, 0.9230783, 0.07692319, 0.4133361, 0.1600011, 0.06666711, 0.2666684, 0.08000053, 0.02666684, 0.6666295, 0.03030134, 0.2878627, 0.9999646, 0.166662, 0.8333098, 0.9999646, 1.000013, 1.000077, 0.4594653, 0.1621642, 0.08108211, 0.2297326, 0.02702737, 0.02702737, 0.4347909, 0.07608842, 0.3152234, 0.02173955, 0.1521768, 0.07691752, 0.2307526, 0.6922577,  0.18183, 0.8182349, 0.7647141, 0.2058846, 0.02941208, 0.09756199, 0.07317149, 0.8292769, 1.000077, 1.000019, 0.9000219, 0.1000024, 0.3200061, 0.5333435, 0.1333359, 0.01333359, 1.000013, 1.000019, 0.9999646, 1.000013, 0.07142926, 0.1428585, 0.1071439, 0.678578, 0.2368441, 0.1842121, 0.1637441, 0.2046801, 0.07017603, 0.1374281, 1.000013, 0.2043036, 0.05376411, 0.1720452, 0.1720452, 0.1075282, 0.301079, 0.9000179, 0.100002, 0.9998884, 0.1538325, 0.8460787, 0.7386576, 0.01136396, 0.05681982, 0.02272793, 0.1704594, 1.000024, 1.000077, 0.7407563, 0.2564157, 0.002849063, 0.9999646 ] 
},
"R":       30,
"lambda.step":      0.1,
"plot.opts": {
 "xlab": "PC1",
"ylab": "PC2" 
},
"topic.order": [ 1, 6, 3, 4, 5, 2 ] 
}